{"imgdata":[{"file":"","width_original":"50","width":"50","height_original":"71","height":"71"},{"clusters":{"cluster":[[{"id":"0","n":"1455","f":"0.409859"},{"rgb":[{"r":"236","g":"200","b":"173"}]},{"hex":[{"hex":"#ECC8AD"}]},{"hsv":[{"h":"26","s":"27","v":"93"}]},{"lab":[{"l":"83","a":"9","b":"18"}]},{"lch":[{"l":"83","c":"20","h":"65"}]},{"xyz":[{"x":"0.63","y":"0.62","z":"0.48"}]},{"cmyk":[{"c":"0","m":"14","y":"25","k":"7"}]},{"neighbours":"desert_sand[1905][237,201,175](0.3):peach_puff[2062][238,203,173](2.2):peachpuff[2063][238,203,173](2.2):light_wood[1904][233,194,166](2.5):flesh[1862][245,204,176](2.5):cashmere[1763][230,190,165](3.8):desert_sand[1768][239,205,184](3.8):pancho[2277][237,205,171](4.0):just_right[1829][236,205,185](4.4):apricot[1800][251,206,177](4.8)"},{"num_neighbours_maxdE":"10"},{"tags":"light:apricot:cashmere:desert:flesh:just:pancho:peachpuff:puff:right:sand:wood:peach"}],[{"id":"1","n":"1402","f":"0.394930"},{"rgb":[{"r":"227","g":"171","b":"129"}]},{"hex":[{"hex":"#E3AB81"}]},{"hsv":[{"h":"26","s":"43","v":"89"}]},{"lab":[{"l":"74","a":"15","b":"30"}]},{"lch":[{"l":"74","c":"33","h":"63"}]},{"xyz":[{"x":"0.5","y":"0.47","z":"0.27"}]},{"cmyk":[{"c":"0","m":"22","y":"39","k":"11"}]},{"neighbours":"manhattan[2058][226,175,128](2.8):tumbleweed[1792][222,166,129](3.5):light_tangelo[1733][231,174,139](4.1):tumbleweed[1793][222,170,136](4.6):tacao[2000][237,179,129](5.2):light_orange[2135][231,185,139](5.7):deja_vu[2227][215,174,129](6.3):whiskey[1826][213,154,111](6.6):muka[2354][210,172,125](7.4):brandy[2275][220,182,138](7.7)"},{"num_neighbours_maxdE":"4"},{"tags":"light:manhattan:tangelo:tumbleweed"}],[{"id":"2","n":"362","f":"0.101972"},{"rgb":[{"r":"165","g":"125","b":"116"}]},{"hex":[{"hex":"#A57D74"}]},{"hsv":[{"h":"12","s":"30","v":"65"}]},{"lab":[{"l":"56","a":"14","b":"11"}]},{"lch":[{"l":"56","c":"18","h":"39"}]},{"xyz":[{"x":"0.26","y":"0.24","z":"0.2"}]},{"cmyk":[{"c":"0","m":"16","y":"19","k":"35"}]},{"neighbours":"burnished_brown[887][161,122,116](2.2):pharlap[842][163,128,123](3.3):reddish_grey[839][153,117,112](4.4):grayish_red[454][168,125,125](4.9):grayish_vermilion[1331][168,136,125](5.1):brandy_rose[1097][182,133,122](5.3):quarter_lumberjack[807][150,112,107](5.4):hemp[1392][152,125,115](5.6):beaver[1685][159,129,112](6.0):toast[1243][154,110,97](6.2)"},{"num_neighbours_maxdE":"4"},{"tags":"burnished:grayish:pharlap:reddish:brown:grey:red"}],[{"id":"3","n":"199","f":"0.056056"},{"rgb":[{"r":"115","g":"108","b":"110"}]},{"hex":[{"hex":"#736C6E"}]},{"hsv":[{"h":"339","s":"6","v":"45"}]},{"lab":[{"l":"46","a":"3","b":"0"}]},{"lch":[{"l":"46","c":"3","h":"353"}]},{"xyz":[{"x":"0.15","y":"0.15","z":"0.17"}]},{"cmyk":[{"c":"0","m":"3","y":"2","k":"55"}]},{"neighbours":"weathered_grey[401][119,111,111](2.0):identity[400][110,103,103](2.6):scarpa_flow[7317][107,106,108](2.6):blast_grey[2294][113,110,107](3.1):half_sidewinder[8012][111,103,108](3.1):dove_grey[360][109,108,108](3.1):grey[7469][110,110,110](3.1):grey[7471][112,112,112](3.2):empress[107][124,113,115](3.3):scorpion[8236][106,100,102](3.3)"},{"num_neighbours_maxdE":"10"},{"tags":"blast:dove:empress:flow:half:identity:scarpa:scorpion:sidewinder:weathered:grey"}],[{"id":"4","n":"132","f":"0.037183"},{"rgb":[{"r":"211","g":"83","b":"68"}]},{"hex":[{"hex":"#D35344"}]},{"hsv":[{"h":"6","s":"68","v":"83"}]},{"lab":[{"l":"52","a":"49","b":"35"}]},{"lch":[{"l":"52","c":"60","h":"35"}]},{"xyz":[{"x":"0.31","y":"0.2","z":"0.08"}]},{"cmyk":[{"c":"0","m":"50","y":"56","k":"17"}]},{"neighbours":"daredevil[994][203,72,59](3.8):pale_red[822][217,84,77](4.1):catalyst[1029][200,82,65](4.4):filmpro_orange[1061][212,80,60](4.4):tomato[1103][205,79,57](4.4):valencia[854][212,87,78](4.9):jelly_bean[1032][218,97,78](5.2):mojo[1027][192,71,55](5.6):coral[1104][205,91,69](5.6):dark_coral[1105][205,91,69](5.6)"},{"num_neighbours_maxdE":"6"},{"tags":"pale:catalyst:daredevil:filmpro:tomato:valencia:orange:red"}]]}},{"stats":{"lab":{"avg":["13.000000","22.000000","74.000000"],"median":["12.000000","21.000000","75.000000"],"min":["-8.000000","-15.000000","27.000000"],"max":["59.000000","48.000000","95.000000"]},"rgb":{"avg":["142.000000","172.000000","218.000000"],"median":["134.000000","175.000000","229.000000"],"min":["47.000000","58.000000","63.000000"],"max":["236.000000","241.000000","253.000000"]}}},{"histogram":{"lab":{"a":[[{"bin":"-8.000000"},"3"],[{"bin":"-7.000000"},"2"],[{"bin":"-6.000000"},"1"],[{"bin":"-5.000000"},"4"],[{"bin":"-4.000000"},"6"],[{"bin":"-3.000000"},"11"],[{"bin":"-2.000000"},"12"],[{"bin":"-1.000000"},"14"],[{"bin":"0.000000"},"13"],[{"bin":"1.000000"},"11"],[{"bin":"2.000000"},"53"],[{"bin":"3.000000"},"41"],[{"bin":"4.000000"},"76"],[{"bin":"5.000000"},"62"],[{"bin":"6.000000"},"54"],[{"bin":"7.000000"},"108"],[{"bin":"8.000000"},"324"],[{"bin":"9.000000"},"497"],[{"bin":"10.000000"},"273"],[{"bin":"11.000000"},"152"],[{"bin":"12.000000"},"129"],[{"bin":"13.000000"},"168"],[{"bin":"14.000000"},"306"],[{"bin":"15.000000"},"288"],[{"bin":"16.000000"},"302"],[{"bin":"17.000000"},"285"],[{"bin":"18.000000"},"35"],[{"bin":"19.000000"},"49"],[{"bin":"20.000000"},"37"],[{"bin":"21.000000"},"21"],[{"bin":"22.000000"},"18"],[{"bin":"23.000000"},"17"],[{"bin":"24.000000"},"6"],[{"bin":"25.000000"},"7"],[{"bin":"26.000000"},"5"],[{"bin":"27.000000"},"4"],[{"bin":"28.000000"},"8"],[{"bin":"29.000000"},"7"],[{"bin":"30.000000"},"4"],[{"bin":"31.000000"},"1"],[{"bin":"32.000000"},"2"],[{"bin":"33.000000"},"3"],[{"bin":"34.000000"},"2"],[{"bin":"35.000000"},"1"],[{"bin":"36.000000"},"3"],[{"bin":"37.000000"},"2"],[{"bin":"38.000000"},"1"],[{"bin":"39.000000"},"4"],[{"bin":"40.000000"},"1"],[{"bin":"41.000000"},"3"],[{"bin":"42.000000"},"3"],[{"bin":"43.000000"},"3"],[{"bin":"44.000000"},"4"],[{"bin":"45.000000"},"3"],[{"bin":"46.000000"},"6"],[{"bin":"47.000000"},"7"],[{"bin":"48.000000"},"4"],[{"bin":"49.000000"},"7"],[{"bin":"50.000000"},"7"],[{"bin":"51.000000"},"8"],[{"bin":"52.000000"},"10"],[{"bin":"53.000000"},"14"],[{"bin":"54.000000"},"8"],[{"bin":"55.000000"},"10"],[{"bin":"56.000000"},"8"],[{"bin":"57.000000"},"4"],[{"bin":"58.000000"},"5"],[{"bin":"59.000000"},"3"]],"b":[[{"bin":"-15.000000"},"1"],[{"bin":"-14.000000"},"1"],[{"bin":"-13.000000"},"2"],[{"bin":"-12.000000"},"5"],[{"bin":"-11.000000"},"4"],[{"bin":"-10.000000"},"9"],[{"bin":"-9.000000"},"2"],[{"bin":"-8.000000"},"10"],[{"bin":"-7.000000"},"7"],[{"bin":"-6.000000"},"6"],[{"bin":"-5.000000"},"1"],[{"bin":"-4.000000"},"8"],[{"bin":"-3.000000"},"7"],[{"bin":"-2.000000"},"9"],[{"bin":"-1.000000"},"5"],[{"bin":"0.000000"},"16"],[{"bin":"1.000000"},"11"],[{"bin":"2.000000"},"22"],[{"bin":"3.000000"},"26"],[{"bin":"4.000000"},"29"],[{"bin":"5.000000"},"28"],[{"bin":"6.000000"},"47"],[{"bin":"7.000000"},"51"],[{"bin":"8.000000"},"32"],[{"bin":"9.000000"},"46"],[{"bin":"10.000000"},"71"],[{"bin":"11.000000"},"38"],[{"bin":"12.000000"},"47"],[{"bin":"13.000000"},"39"],[{"bin":"14.000000"},"51"],[{"bin":"15.000000"},"91"],[{"bin":"16.000000"},"87"],[{"bin":"17.000000"},"102"],[{"bin":"18.000000"},"289"],[{"bin":"19.000000"},"220"],[{"bin":"20.000000"},"170"],[{"bin":"21.000000"},"213"],[{"bin":"22.000000"},"114"],[{"bin":"23.000000"},"49"],[{"bin":"24.000000"},"66"],[{"bin":"25.000000"},"51"],[{"bin":"26.000000"},"34"],[{"bin":"27.000000"},"81"],[{"bin":"28.000000"},"156"],[{"bin":"29.000000"},"231"],[{"bin":"30.000000"},"510"],[{"bin":"31.000000"},"159"],[{"bin":"32.000000"},"59"],[{"bin":"33.000000"},"62"],[{"bin":"34.000000"},"57"],[{"bin":"35.000000"},"44"],[{"bin":"36.000000"},"12"],[{"bin":"37.000000"},"11"],[{"bin":"38.000000"},"11"],[{"bin":"39.000000"},"10"],[{"bin":"40.000000"},"18"],[{"bin":"41.000000"},"4"],[{"bin":"42.000000"},"5"],[{"bin":"43.000000"},"2"],[{"bin":"48.000000"},"1"]],"l":[[{"bin":"27.000000"},"2"],[{"bin":"28.000000"},"1"],[{"bin":"29.000000"},"1"],[{"bin":"31.000000"},"1"],[{"bin":"32.000000"},"1"],[{"bin":"33.000000"},"3"],[{"bin":"34.000000"},"1"],[{"bin":"35.000000"},"2"],[{"bin":"36.000000"},"4"],[{"bin":"37.000000"},"5"],[{"bin":"38.000000"},"9"],[{"bin":"39.000000"},"12"],[{"bin":"40.000000"},"10"],[{"bin":"41.000000"},"20"],[{"bin":"42.000000"},"9"],[{"bin":"43.000000"},"9"],[{"bin":"44.000000"},"17"],[{"bin":"45.000000"},"21"],[{"bin":"46.000000"},"21"],[{"bin":"47.000000"},"14"],[{"bin":"48.000000"},"32"],[{"bin":"49.000000"},"20"],[{"bin":"50.000000"},"43"],[{"bin":"51.000000"},"39"],[{"bin":"52.000000"},"45"],[{"bin":"53.000000"},"40"],[{"bin":"54.000000"},"47"],[{"bin":"55.000000"},"31"],[{"bin":"56.000000"},"24"],[{"bin":"57.000000"},"33"],[{"bin":"58.000000"},"20"],[{"bin":"59.000000"},"22"],[{"bin":"60.000000"},"25"],[{"bin":"61.000000"},"12"],[{"bin":"62.000000"},"17"],[{"bin":"63.000000"},"15"],[{"bin":"64.000000"},"16"],[{"bin":"65.000000"},"6"],[{"bin":"66.000000"},"13"],[{"bin":"67.000000"},"13"],[{"bin":"68.000000"},"11"],[{"bin":"69.000000"},"26"],[{"bin":"70.000000"},"37"],[{"bin":"71.000000"},"88"],[{"bin":"72.000000"},"118"],[{"bin":"73.000000"},"177"],[{"bin":"74.000000"},"298"],[{"bin":"75.000000"},"393"],[{"bin":"76.000000"},"278"],[{"bin":"77.000000"},"50"],[{"bin":"78.000000"},"36"],[{"bin":"79.000000"},"59"],[{"bin":"80.000000"},"88"],[{"bin":"81.000000"},"68"],[{"bin":"82.000000"},"96"],[{"bin":"83.000000"},"243"],[{"bin":"84.000000"},"381"],[{"bin":"85.000000"},"266"],[{"bin":"86.000000"},"72"],[{"bin":"87.000000"},"15"],[{"bin":"88.000000"},"3"],[{"bin":"89.000000"},"14"],[{"bin":"90.000000"},"13"],[{"bin":"91.000000"},"15"],[{"bin":"92.000000"},"7"],[{"bin":"93.000000"},"17"],[{"bin":"94.000000"},"4"],[{"bin":"95.000000"},"1"]]},"rgb":{"b":[[{"bin":"47.000000"},"1"],[{"bin":"50.000000"},"1"],[{"bin":"51.000000"},"1"],[{"bin":"53.000000"},"2"],[{"bin":"54.000000"},"1"],[{"bin":"55.000000"},"2"],[{"bin":"56.000000"},"4"],[{"bin":"57.000000"},"2"],[{"bin":"58.000000"},"4"],[{"bin":"59.000000"},"10"],[{"bin":"60.000000"},"6"],[{"bin":"61.000000"},"5"],[{"bin":"62.000000"},"5"],[{"bin":"63.000000"},"2"],[{"bin":"64.000000"},"9"],[{"bin":"65.000000"},"8"],[{"bin":"66.000000"},"4"],[{"bin":"67.000000"},"9"],[{"bin":"68.000000"},"8"],[{"bin":"69.000000"},"9"],[{"bin":"70.000000"},"7"],[{"bin":"71.000000"},"3"],[{"bin":"72.000000"},"5"],[{"bin":"73.000000"},"4"],[{"bin":"74.000000"},"4"],[{"bin":"75.000000"},"6"],[{"bin":"76.000000"},"5"],[{"bin":"77.000000"},"5"],[{"bin":"78.000000"},"4"],[{"bin":"79.000000"},"3"],[{"bin":"80.000000"},"3"],[{"bin":"81.000000"},"1"],[{"bin":"82.000000"},"3"],[{"bin":"83.000000"},"6"],[{"bin":"84.000000"},"4"],[{"bin":"85.000000"},"5"],[{"bin":"86.000000"},"9"],[{"bin":"87.000000"},"5"],[{"bin":"88.000000"},"7"],[{"bin":"89.000000"},"4"],[{"bin":"90.000000"},"5"],[{"bin":"91.000000"},"4"],[{"bin":"92.000000"},"10"],[{"bin":"93.000000"},"5"],[{"bin":"94.000000"},"9"],[{"bin":"95.000000"},"7"],[{"bin":"96.000000"},"19"],[{"bin":"97.000000"},"7"],[{"bin":"98.000000"},"11"],[{"bin":"99.000000"},"8"],[{"bin":"100.000000"},"9"],[{"bin":"101.000000"},"14"],[{"bin":"102.000000"},"11"],[{"bin":"103.000000"},"10"],[{"bin":"104.000000"},"12"],[{"bin":"105.000000"},"14"],[{"bin":"106.000000"},"19"],[{"bin":"107.000000"},"14"],[{"bin":"108.000000"},"11"],[{"bin":"109.000000"},"14"],[{"bin":"110.000000"},"12"],[{"bin":"111.000000"},"9"],[{"bin":"112.000000"},"26"],[{"bin":"113.000000"},"17"],[{"bin":"114.000000"},"22"],[{"bin":"115.000000"},"19"],[{"bin":"116.000000"},"24"],[{"bin":"117.000000"},"14"],[{"bin":"118.000000"},"25"],[{"bin":"119.000000"},"18"],[{"bin":"120.000000"},"39"],[{"bin":"121.000000"},"72"],[{"bin":"122.000000"},"76"],[{"bin":"123.000000"},"51"],[{"bin":"124.000000"},"48"],[{"bin":"125.000000"},"54"],[{"bin":"126.000000"},"69"],[{"bin":"127.000000"},"76"],[{"bin":"128.000000"},"77"],[{"bin":"129.000000"},"104"],[{"bin":"130.000000"},"98"],[{"bin":"131.000000"},"100"],[{"bin":"132.000000"},"109"],[{"bin":"133.000000"},"118"],[{"bin":"134.000000"},"100"],[{"bin":"135.000000"},"89"],[{"bin":"136.000000"},"54"],[{"bin":"137.000000"},"17"],[{"bin":"138.000000"},"20"],[{"bin":"139.000000"},"12"],[{"bin":"140.000000"},"2"],[{"bin":"141.000000"},"7"],[{"bin":"142.000000"},"10"],[{"bin":"143.000000"},"5"],[{"bin":"144.000000"},"7"],[{"bin":"145.000000"},"8"],[{"bin":"146.000000"},"9"],[{"bin":"147.000000"},"17"],[{"bin":"148.000000"},"9"],[{"bin":"149.000000"},"13"],[{"bin":"150.000000"},"14"],[{"bin":"151.000000"},"17"],[{"bin":"152.000000"},"28"],[{"bin":"153.000000"},"28"],[{"bin":"154.000000"},"28"],[{"bin":"155.000000"},"13"],[{"bin":"156.000000"},"21"],[{"bin":"157.000000"},"19"],[{"bin":"158.000000"},"25"],[{"bin":"159.000000"},"13"],[{"bin":"160.000000"},"17"],[{"bin":"161.000000"},"20"],[{"bin":"162.000000"},"24"],[{"bin":"163.000000"},"12"],[{"bin":"164.000000"},"28"],[{"bin":"165.000000"},"33"],[{"bin":"166.000000"},"37"],[{"bin":"167.000000"},"55"],[{"bin":"168.000000"},"46"],[{"bin":"169.000000"},"73"],[{"bin":"170.000000"},"67"],[{"bin":"171.000000"},"88"],[{"bin":"172.000000"},"61"],[{"bin":"173.000000"},"55"],[{"bin":"174.000000"},"51"],[{"bin":"175.000000"},"85"],[{"bin":"176.000000"},"64"],[{"bin":"177.000000"},"90"],[{"bin":"178.000000"},"85"],[{"bin":"179.000000"},"61"],[{"bin":"180.000000"},"58"],[{"bin":"181.000000"},"29"],[{"bin":"182.000000"},"28"],[{"bin":"183.000000"},"19"],[{"bin":"184.000000"},"11"],[{"bin":"185.000000"},"5"],[{"bin":"186.000000"},"5"],[{"bin":"187.000000"},"1"],[{"bin":"188.000000"},"4"],[{"bin":"189.000000"},"1"],[{"bin":"190.000000"},"4"],[{"bin":"191.000000"},"1"],[{"bin":"204.000000"},"1"],[{"bin":"205.000000"},"12"],[{"bin":"206.000000"},"1"],[{"bin":"207.000000"},"10"],[{"bin":"208.000000"},"2"],[{"bin":"209.000000"},"2"],[{"bin":"210.000000"},"1"],[{"bin":"211.000000"},"1"],[{"bin":"212.000000"},"3"],[{"bin":"214.000000"},"2"],[{"bin":"215.000000"},"6"],[{"bin":"216.000000"},"1"],[{"bin":"218.000000"},"1"],[{"bin":"221.000000"},"7"],[{"bin":"222.000000"},"7"],[{"bin":"223.000000"},"1"],[{"bin":"224.000000"},"1"],[{"bin":"225.000000"},"7"],[{"bin":"226.000000"},"3"],[{"bin":"228.000000"},"1"],[{"bin":"236.000000"},"1"]],"g":[[{"bin":"58.000000"},"1"],[{"bin":"62.000000"},"3"],[{"bin":"65.000000"},"1"],[{"bin":"66.000000"},"3"],[{"bin":"67.000000"},"2"],[{"bin":"68.000000"},"2"],[{"bin":"69.000000"},"4"],[{"bin":"70.000000"},"2"],[{"bin":"71.000000"},"1"],[{"bin":"72.000000"},"2"],[{"bin":"73.000000"},"6"],[{"bin":"74.000000"},"6"],[{"bin":"75.000000"},"6"],[{"bin":"76.000000"},"4"],[{"bin":"77.000000"},"12"],[{"bin":"78.000000"},"9"],[{"bin":"79.000000"},"7"],[{"bin":"80.000000"},"11"],[{"bin":"81.000000"},"7"],[{"bin":"82.000000"},"11"],[{"bin":"83.000000"},"6"],[{"bin":"84.000000"},"9"],[{"bin":"85.000000"},"13"],[{"bin":"86.000000"},"8"],[{"bin":"87.000000"},"11"],[{"bin":"88.000000"},"7"],[{"bin":"89.000000"},"6"],[{"bin":"90.000000"},"8"],[{"bin":"91.000000"},"10"],[{"bin":"92.000000"},"12"],[{"bin":"93.000000"},"7"],[{"bin":"94.000000"},"7"],[{"bin":"95.000000"},"6"],[{"bin":"96.000000"},"3"],[{"bin":"97.000000"},"7"],[{"bin":"98.000000"},"9"],[{"bin":"99.000000"},"8"],[{"bin":"100.000000"},"5"],[{"bin":"101.000000"},"5"],[{"bin":"102.000000"},"12"],[{"bin":"103.000000"},"7"],[{"bin":"104.000000"},"8"],[{"bin":"105.000000"},"8"],[{"bin":"106.000000"},"15"],[{"bin":"107.000000"},"7"],[{"bin":"108.000000"},"15"],[{"bin":"109.000000"},"9"],[{"bin":"110.000000"},"12"],[{"bin":"111.000000"},"13"],[{"bin":"112.000000"},"9"],[{"bin":"113.000000"},"12"],[{"bin":"114.000000"},"7"],[{"bin":"115.000000"},"7"],[{"bin":"116.000000"},"9"],[{"bin":"117.000000"},"12"],[{"bin":"118.000000"},"7"],[{"bin":"119.000000"},"9"],[{"bin":"120.000000"},"9"],[{"bin":"121.000000"},"14"],[{"bin":"122.000000"},"12"],[{"bin":"123.000000"},"9"],[{"bin":"124.000000"},"13"],[{"bin":"125.000000"},"4"],[{"bin":"126.000000"},"6"],[{"bin":"127.000000"},"6"],[{"bin":"128.000000"},"8"],[{"bin":"129.000000"},"5"],[{"bin":"130.000000"},"3"],[{"bin":"131.000000"},"5"],[{"bin":"132.000000"},"7"],[{"bin":"133.000000"},"10"],[{"bin":"134.000000"},"10"],[{"bin":"135.000000"},"3"],[{"bin":"136.000000"},"13"],[{"bin":"137.000000"},"10"],[{"bin":"138.000000"},"9"],[{"bin":"139.000000"},"6"],[{"bin":"140.000000"},"7"],[{"bin":"141.000000"},"7"],[{"bin":"142.000000"},"5"],[{"bin":"143.000000"},"3"],[{"bin":"144.000000"},"3"],[{"bin":"145.000000"},"3"],[{"bin":"146.000000"},"6"],[{"bin":"147.000000"},"1"],[{"bin":"148.000000"},"9"],[{"bin":"149.000000"},"8"],[{"bin":"150.000000"},"7"],[{"bin":"151.000000"},"9"],[{"bin":"152.000000"},"4"],[{"bin":"153.000000"},"4"],[{"bin":"154.000000"},"8"],[{"bin":"155.000000"},"14"],[{"bin":"156.000000"},"5"],[{"bin":"157.000000"},"10"],[{"bin":"158.000000"},"6"],[{"bin":"159.000000"},"25"],[{"bin":"160.000000"},"21"],[{"bin":"161.000000"},"24"],[{"bin":"162.000000"},"39"],[{"bin":"163.000000"},"40"],[{"bin":"164.000000"},"44"],[{"bin":"165.000000"},"28"],[{"bin":"166.000000"},"30"],[{"bin":"167.000000"},"51"],[{"bin":"168.000000"},"67"],[{"bin":"169.000000"},"89"],[{"bin":"170.000000"},"84"],[{"bin":"171.000000"},"101"],[{"bin":"172.000000"},"134"],[{"bin":"173.000000"},"109"],[{"bin":"174.000000"},"114"],[{"bin":"175.000000"},"132"],[{"bin":"176.000000"},"138"],[{"bin":"177.000000"},"69"],[{"bin":"178.000000"},"38"],[{"bin":"179.000000"},"26"],[{"bin":"180.000000"},"13"],[{"bin":"181.000000"},"8"],[{"bin":"182.000000"},"6"],[{"bin":"183.000000"},"10"],[{"bin":"184.000000"},"13"],[{"bin":"185.000000"},"11"],[{"bin":"186.000000"},"13"],[{"bin":"187.000000"},"21"],[{"bin":"188.000000"},"27"],[{"bin":"189.000000"},"19"],[{"bin":"190.000000"},"34"],[{"bin":"191.000000"},"22"],[{"bin":"192.000000"},"18"],[{"bin":"193.000000"},"37"],[{"bin":"194.000000"},"25"],[{"bin":"195.000000"},"41"],[{"bin":"196.000000"},"31"],[{"bin":"197.000000"},"27"],[{"bin":"198.000000"},"43"],[{"bin":"199.000000"},"75"],[{"bin":"200.000000"},"98"],[{"bin":"201.000000"},"99"],[{"bin":"202.000000"},"118"],[{"bin":"203.000000"},"127"],[{"bin":"204.000000"},"131"],[{"bin":"205.000000"},"121"],[{"bin":"206.000000"},"70"],[{"bin":"207.000000"},"39"],[{"bin":"208.000000"},"27"],[{"bin":"209.000000"},"17"],[{"bin":"210.000000"},"7"],[{"bin":"211.000000"},"7"],[{"bin":"212.000000"},"5"],[{"bin":"213.000000"},"7"],[{"bin":"214.000000"},"2"],[{"bin":"216.000000"},"1"],[{"bin":"219.000000"},"1"],[{"bin":"220.000000"},"6"],[{"bin":"221.000000"},"7"],[{"bin":"222.000000"},"3"],[{"bin":"223.000000"},"7"],[{"bin":"225.000000"},"9"],[{"bin":"226.000000"},"6"],[{"bin":"227.000000"},"3"],[{"bin":"228.000000"},"1"],[{"bin":"231.000000"},"6"],[{"bin":"232.000000"},"9"],[{"bin":"233.000000"},"1"],[{"bin":"234.000000"},"7"],[{"bin":"235.000000"},"2"],[{"bin":"238.000000"},"2"],[{"bin":"241.000000"},"1"]],"r":[[{"bin":"63.000000"},"1"],[{"bin":"64.000000"},"1"],[{"bin":"65.000000"},"1"],[{"bin":"66.000000"},"1"],[{"bin":"67.000000"},"1"],[{"bin":"69.000000"},"1"],[{"bin":"70.000000"},"1"],[{"bin":"71.000000"},"1"],[{"bin":"72.000000"},"2"],[{"bin":"73.000000"},"2"],[{"bin":"74.000000"},"2"],[{"bin":"76.000000"},"3"],[{"bin":"77.000000"},"2"],[{"bin":"78.000000"},"5"],[{"bin":"80.000000"},"1"],[{"bin":"82.000000"},"1"],[{"bin":"83.000000"},"1"],[{"bin":"84.000000"},"4"],[{"bin":"87.000000"},"8"],[{"bin":"88.000000"},"1"],[{"bin":"89.000000"},"2"],[{"bin":"90.000000"},"3"],[{"bin":"92.000000"},"1"],[{"bin":"93.000000"},"3"],[{"bin":"95.000000"},"2"],[{"bin":"96.000000"},"4"],[{"bin":"99.000000"},"2"],[{"bin":"100.000000"},"1"],[{"bin":"101.000000"},"1"],[{"bin":"102.000000"},"1"],[{"bin":"103.000000"},"1"],[{"bin":"105.000000"},"2"],[{"bin":"106.000000"},"3"],[{"bin":"107.000000"},"3"],[{"bin":"108.000000"},"1"],[{"bin":"109.000000"},"4"],[{"bin":"110.000000"},"1"],[{"bin":"111.000000"},"4"],[{"bin":"112.000000"},"2"],[{"bin":"113.000000"},"2"],[{"bin":"114.000000"},"5"],[{"bin":"115.000000"},"4"],[{"bin":"116.000000"},"1"],[{"bin":"117.000000"},"1"],[{"bin":"118.000000"},"5"],[{"bin":"119.000000"},"3"],[{"bin":"120.000000"},"3"],[{"bin":"121.000000"},"5"],[{"bin":"122.000000"},"3"],[{"bin":"124.000000"},"4"],[{"bin":"125.000000"},"3"],[{"bin":"126.000000"},"5"],[{"bin":"127.000000"},"4"],[{"bin":"128.000000"},"2"],[{"bin":"129.000000"},"7"],[{"bin":"130.000000"},"4"],[{"bin":"131.000000"},"6"],[{"bin":"132.000000"},"4"],[{"bin":"133.000000"},"4"],[{"bin":"134.000000"},"4"],[{"bin":"135.000000"},"7"],[{"bin":"136.000000"},"7"],[{"bin":"137.000000"},"6"],[{"bin":"138.000000"},"8"],[{"bin":"139.000000"},"5"],[{"bin":"140.000000"},"5"],[{"bin":"141.000000"},"7"],[{"bin":"142.000000"},"5"],[{"bin":"143.000000"},"5"],[{"bin":"144.000000"},"10"],[{"bin":"145.000000"},"6"],[{"bin":"146.000000"},"10"],[{"bin":"147.000000"},"4"],[{"bin":"148.000000"},"10"],[{"bin":"149.000000"},"7"],[{"bin":"150.000000"},"9"],[{"bin":"151.000000"},"7"],[{"bin":"152.000000"},"10"],[{"bin":"153.000000"},"9"],[{"bin":"154.000000"},"2"],[{"bin":"155.000000"},"6"],[{"bin":"156.000000"},"10"],[{"bin":"157.000000"},"7"],[{"bin":"158.000000"},"8"],[{"bin":"159.000000"},"13"],[{"bin":"160.000000"},"8"],[{"bin":"161.000000"},"8"],[{"bin":"162.000000"},"7"],[{"bin":"163.000000"},"9"],[{"bin":"164.000000"},"10"],[{"bin":"165.000000"},"15"],[{"bin":"166.000000"},"12"],[{"bin":"167.000000"},"10"],[{"bin":"168.000000"},"8"],[{"bin":"169.000000"},"7"],[{"bin":"170.000000"},"10"],[{"bin":"171.000000"},"7"],[{"bin":"172.000000"},"6"],[{"bin":"173.000000"},"7"],[{"bin":"174.000000"},"6"],[{"bin":"175.000000"},"6"],[{"bin":"176.000000"},"9"],[{"bin":"177.000000"},"6"],[{"bin":"178.000000"},"9"],[{"bin":"179.000000"},"5"],[{"bin":"180.000000"},"5"],[{"bin":"181.000000"},"2"],[{"bin":"182.000000"},"6"],[{"bin":"183.000000"},"6"],[{"bin":"184.000000"},"2"],[{"bin":"185.000000"},"5"],[{"bin":"186.000000"},"4"],[{"bin":"187.000000"},"4"],[{"bin":"188.000000"},"3"],[{"bin":"189.000000"},"7"],[{"bin":"190.000000"},"5"],[{"bin":"191.000000"},"3"],[{"bin":"192.000000"},"3"],[{"bin":"193.000000"},"3"],[{"bin":"195.000000"},"5"],[{"bin":"196.000000"},"7"],[{"bin":"197.000000"},"3"],[{"bin":"198.000000"},"6"],[{"bin":"199.000000"},"5"],[{"bin":"200.000000"},"3"],[{"bin":"201.000000"},"9"],[{"bin":"202.000000"},"7"],[{"bin":"203.000000"},"7"],[{"bin":"204.000000"},"3"],[{"bin":"205.000000"},"6"],[{"bin":"206.000000"},"11"],[{"bin":"207.000000"},"5"],[{"bin":"208.000000"},"6"],[{"bin":"209.000000"},"13"],[{"bin":"210.000000"},"8"],[{"bin":"211.000000"},"14"],[{"bin":"212.000000"},"15"],[{"bin":"213.000000"},"16"],[{"bin":"214.000000"},"7"],[{"bin":"215.000000"},"14"],[{"bin":"216.000000"},"7"],[{"bin":"217.000000"},"16"],[{"bin":"218.000000"},"22"],[{"bin":"219.000000"},"26"],[{"bin":"220.000000"},"45"],[{"bin":"221.000000"},"74"],[{"bin":"222.000000"},"93"],[{"bin":"223.000000"},"81"],[{"bin":"224.000000"},"73"],[{"bin":"225.000000"},"97"],[{"bin":"226.000000"},"137"],[{"bin":"227.000000"},"147"],[{"bin":"228.000000"},"152"],[{"bin":"229.000000"},"167"],[{"bin":"230.000000"},"172"],[{"bin":"231.000000"},"141"],[{"bin":"232.000000"},"110"],[{"bin":"233.000000"},"74"],[{"bin":"234.000000"},"41"],[{"bin":"235.000000"},"39"],[{"bin":"236.000000"},"46"],[{"bin":"237.000000"},"77"],[{"bin":"238.000000"},"58"],[{"bin":"239.000000"},"84"],[{"bin":"240.000000"},"205"],[{"bin":"241.000000"},"214"],[{"bin":"242.000000"},"186"],[{"bin":"243.000000"},"98"],[{"bin":"244.000000"},"62"],[{"bin":"245.000000"},"22"],[{"bin":"246.000000"},"24"],[{"bin":"247.000000"},"9"],[{"bin":"248.000000"},"7"],[{"bin":"249.000000"},"2"],[{"bin":"250.000000"},"2"],[{"bin":"251.000000"},"3"],[{"bin":"253.000000"},"1"]]}}}]}