{"imgdata":[{"file":"","width_original":"50","width":"50","height_original":"73","height":"73"},{"clusters":{"cluster":[[{"id":"0","n":"1395","f":"0.382192"},{"rgb":[{"r":"235","g":"223","b":"200"}]},{"hex":[{"hex":"#EBDFC8"}]},{"hsv":[{"h":"40","s":"15","v":"92"}]},{"lab":[{"l":"89","a":"0","b":"13"}]},{"lch":[{"l":"89","c":"13","h":"89"}]},{"xyz":[{"x":"0.71","y":"0.75","z":"0.65"}]},{"cmyk":[{"c":"0","m":"5","y":"14","k":"8"}]},{"neighbours":"double_villa_white[3192][230,220,197](1.3):pearl[3196][234,224,200](1.4):pearl_lusta[3197][234,224,200](1.4):eighth_pavlova[3253][234,224,199](1.4):wildflower[2840][241,226,201](1.6):orange_white[3406][234,227,205](1.7):bleach_white[3010][235,225,206](1.9):quarter_haystack[2517][238,220,196](2.1):half_spanish_white[2954][230,219,199](2.1):triple_pearl_lusta[3198][235,223,195](2.3)"},{"num_neighbours_maxdE":"10"},{"tags":"bleach:double:eighth:half:haystack:lusta:pavlova:pearl:quarter:spanish:triple:villa:wildflower:orange:white"}],[{"id":"1","n":"702","f":"0.192329"},{"rgb":[{"r":"181","g":"162","b":"145"}]},{"hex":[{"hex":"#B5A291"}]},{"hsv":[{"h":"28","s":"20","v":"71"}]},{"lab":[{"l":"68","a":"4","b":"11"}]},{"lch":[{"l":"68","c":"12","h":"70"}]},{"xyz":[{"x":"0.37","y":"0.38","z":"0.32"}]},{"cmyk":[{"c":"0","m":"7","y":"14","k":"29"}]},{"neighbours":"paperback[2189][179,161,144](0.9):half_malta[2392][181,166,149](1.7):quarter_gargoyle[2306][178,164,149](1.8):joss[2308][185,168,150](2.6):half_rickshaw[2126][189,167,147](2.9):sandcastle[2348][178,159,137](3.0):triple_tea[2867][170,159,139](3.7):quarter_nullarbor[2391][178,159,136](3.9):double_tea[2981][178,168,148](4.4):cougar[2936][170,160,141](4.5)"},{"num_neighbours_maxdE":"10"},{"tags":"cougar:double:gargoyle:half:joss:malta:nullarbor:paperback:quarter:rickshaw:sandcastle:tea:triple"}],[{"id":"2","n":"694","f":"0.190137"},{"rgb":[{"r":"211","g":"74","b":"54"}]},{"hex":[{"hex":"#D34A36"}]},{"hsv":[{"h":"8","s":"74","v":"83"}]},{"lab":[{"l":"51","a":"53","b":"41"}]},{"lch":[{"l":"51","c":"67","h":"38"}]},{"xyz":[{"x":"0.3","y":"0.19","z":"0.06"}]},{"cmyk":[{"c":"0","m":"54","y":"62","k":"17"}]},{"neighbours":"filmpro_orange[1061][212,80,60](2.8):tomato[1103][205,79,57](4.2):valencia[996][216,68,55](4.2):daredevil[994][203,72,59](5.3):punch[1063][220,67,51](5.7):sunset[1064][220,67,51](5.7):orang_atan[1217][197,79,51](7.1):trinidad[1218][197,79,51](7.1):dark_pastel_red[1180][194,59,34](7.1):flame_pea[1281][218,91,56](7.3)"},{"num_neighbours_maxdE":"3"},{"tags":"filmpro:tomato:valencia:orange"}],[{"id":"3","n":"539","f":"0.147671"},{"rgb":[{"r":"64","g":"97","b":"124"}]},{"hex":[{"hex":"#40617C"}]},{"hsv":[{"h":"207","s":"48","v":"49"}]},{"lab":[{"l":"40","a":"-4","b":"-19"}]},{"lch":[{"l":"40","c":"19","h":"258"}]},{"xyz":[{"x":"0.1","y":"0.11","z":"0.21"}]},{"cmyk":[{"c":"24","m":"11","y":"0","k":"51"}]},{"neighbours":"wavelength[6313][60,104,134](3.7):wedgewood[6406][76,107,136](4.5):matisse[6421][54,92,125](4.6):spray_drift[6370][45,88,119](5.0):blue_bayoux[6256][73,102,121](5.5):chathams_blue[6232][44,89,113](5.5):orient[6255][37,91,119](5.9):blumine[6176][48,92,113](6.0):venice_blue[6388][44,87,120](6.3):sky_blue[6299][74,112,139](6.6)"},{"num_neighbours_maxdE":"4"},{"tags":"drift:matisse:spray:wavelength:wedgewood"}],[{"id":"4","n":"320","f":"0.087671"},{"rgb":[{"r":"94","g":"85","b":"77"}]},{"hex":[{"hex":"#5E554D"}]},{"hsv":[{"h":"28","s":"18","v":"37"}]},{"lab":[{"l":"37","a":"2","b":"6"}]},{"lch":[{"l":"37","c":"6","h":"70"}]},{"xyz":[{"x":"0.09","y":"0.09","z":"0.08"}]},{"cmyk":[{"c":"0","m":"3","y":"7","k":"63"}]},{"neighbours":"half_mondo[2495][98,89,77](2.6):smokey_ash[2856][93,89,82](2.7):alcatraz[1595][90,80,75](2.8):masala[3036][87,83,75](3.0):half_felix[1321][98,83,78](3.0):judge_grey[2460][93,83,70](3.1):triple_stonehenge[2209][102,92,82](3.4):artefact[920][93,82,80](3.6):tabac[2638][88,80,68](3.6):oilskin[3640][85,83,73](3.6)"},{"num_neighbours_maxdE":"10"},{"tags":"alcatraz:artefact:ash:felix:half:judge:masala:mondo:oilskin:smokey:stonehenge:tabac:triple:grey"}]]}},{"stats":{"cmyk":{"avg":["4.000000","25.000000","15.000000","20.000000"],"median":["0.000000","15.000000","5.000000","12.500000"],"min":["0.000000","0.000000","0.000000","0.000000"],"max":["38.000000","92.000000","73.000000","76.000000"]},"hsv":{"avg":["34.000000","32.000000","75.000000"],"median":["40.000000","17.000000","85.000000"],"min":["0.000000","0.000000","8.000000"],"max":["360.000000","93.000000","100.000000"]},"lab":{"avg":["10.000000","13.000000","66.000000"],"median":["0.000000","12.000000","66.000000"],"min":["-14.000000","-34.000000","6.000000"],"max":["68.000000","53.000000","98.000000"]},"lch":{"avg":["24.000000","76.000000","66.000000"],"median":["14.000000","89.000000","66.000000"],"min":["0.000000","6.000000","6.000000"],"max":["85.000000","344.000000","98.000000"]},"rgb":{"avg":["140.000000","152.000000","182.000000"],"median":["145.000000","157.500000","216.000000"],"min":["7.000000","19.000000","19.000000"],"max":["228.000000","253.000000","255.000000"]}}},{"histogram":{"cmyk":{"c":[[{"bin":"0.000000"},"3003"],[{"bin":"1.000000"},"26"],[{"bin":"2.000000"},"31"],[{"bin":"3.000000"},"19"],[{"bin":"4.000000"},"9"],[{"bin":"5.000000"},"5"],[{"bin":"6.000000"},"3"],[{"bin":"7.000000"},"9"],[{"bin":"8.000000"},"5"],[{"bin":"9.000000"},"8"],[{"bin":"10.000000"},"5"],[{"bin":"11.000000"},"5"],[{"bin":"12.000000"},"3"],[{"bin":"13.000000"},"11"],[{"bin":"14.000000"},"8"],[{"bin":"15.000000"},"16"],[{"bin":"16.000000"},"19"],[{"bin":"17.000000"},"19"],[{"bin":"18.000000"},"14"],[{"bin":"19.000000"},"14"],[{"bin":"20.000000"},"23"],[{"bin":"21.000000"},"16"],[{"bin":"22.000000"},"38"],[{"bin":"23.000000"},"22"],[{"bin":"24.000000"},"46"],[{"bin":"25.000000"},"42"],[{"bin":"26.000000"},"19"],[{"bin":"27.000000"},"47"],[{"bin":"28.000000"},"27"],[{"bin":"29.000000"},"58"],[{"bin":"30.000000"},"28"],[{"bin":"31.000000"},"23"],[{"bin":"32.000000"},"13"],[{"bin":"33.000000"},"9"],[{"bin":"34.000000"},"2"],[{"bin":"35.000000"},"2"],[{"bin":"36.000000"},"2"],[{"bin":"38.000000"},"1"]],"k":[[{"bin":"0.000000"},"38"],[{"bin":"1.000000"},"50"],[{"bin":"2.000000"},"135"],[{"bin":"3.000000"},"126"],[{"bin":"4.000000"},"200"],[{"bin":"5.000000"},"169"],[{"bin":"6.000000"},"57"],[{"bin":"7.000000"},"101"],[{"bin":"8.000000"},"63"],[{"bin":"9.000000"},"111"],[{"bin":"10.000000"},"56"],[{"bin":"11.000000"},"91"],[{"bin":"12.000000"},"83"],[{"bin":"13.000000"},"181"],[{"bin":"14.000000"},"183"],[{"bin":"15.000000"},"199"],[{"bin":"16.000000"},"130"],[{"bin":"17.000000"},"35"],[{"bin":"18.000000"},"27"],[{"bin":"19.000000"},"22"],[{"bin":"20.000000"},"36"],[{"bin":"21.000000"},"35"],[{"bin":"22.000000"},"44"],[{"bin":"23.000000"},"23"],[{"bin":"24.000000"},"22"],[{"bin":"25.000000"},"25"],[{"bin":"26.000000"},"16"],[{"bin":"27.000000"},"30"],[{"bin":"28.000000"},"38"],[{"bin":"29.000000"},"31"],[{"bin":"30.000000"},"21"],[{"bin":"31.000000"},"20"],[{"bin":"32.000000"},"15"],[{"bin":"33.000000"},"23"],[{"bin":"34.000000"},"18"],[{"bin":"35.000000"},"22"],[{"bin":"36.000000"},"27"],[{"bin":"37.000000"},"18"],[{"bin":"38.000000"},"32"],[{"bin":"39.000000"},"25"],[{"bin":"40.000000"},"36"],[{"bin":"41.000000"},"36"],[{"bin":"42.000000"},"49"],[{"bin":"43.000000"},"33"],[{"bin":"44.000000"},"59"],[{"bin":"45.000000"},"58"],[{"bin":"46.000000"},"34"],[{"bin":"47.000000"},"84"],[{"bin":"48.000000"},"54"],[{"bin":"49.000000"},"74"],[{"bin":"50.000000"},"36"],[{"bin":"51.000000"},"57"],[{"bin":"52.000000"},"27"],[{"bin":"53.000000"},"26"],[{"bin":"54.000000"},"16"],[{"bin":"55.000000"},"24"],[{"bin":"56.000000"},"20"],[{"bin":"57.000000"},"12"],[{"bin":"58.000000"},"32"],[{"bin":"59.000000"},"20"],[{"bin":"60.000000"},"29"],[{"bin":"61.000000"},"18"],[{"bin":"62.000000"},"27"],[{"bin":"63.000000"},"13"],[{"bin":"64.000000"},"18"],[{"bin":"65.000000"},"12"],[{"bin":"66.000000"},"15"],[{"bin":"67.000000"},"14"],[{"bin":"68.000000"},"12"],[{"bin":"69.000000"},"16"],[{"bin":"70.000000"},"9"],[{"bin":"71.000000"},"15"],[{"bin":"72.000000"},"12"],[{"bin":"73.000000"},"11"],[{"bin":"74.000000"},"8"],[{"bin":"75.000000"},"12"],[{"bin":"76.000000"},"9"],[{"bin":"77.000000"},"8"],[{"bin":"78.000000"},"7"],[{"bin":"79.000000"},"3"],[{"bin":"80.000000"},"3"],[{"bin":"81.000000"},"1"],[{"bin":"82.000000"},"1"],[{"bin":"83.000000"},"2"],[{"bin":"84.000000"},"4"],[{"bin":"85.000000"},"4"],[{"bin":"88.000000"},"1"],[{"bin":"92.000000"},"1"]],"m":[[{"bin":"0.000000"},"184"],[{"bin":"1.000000"},"174"],[{"bin":"2.000000"},"500"],[{"bin":"3.000000"},"293"],[{"bin":"4.000000"},"457"],[{"bin":"5.000000"},"284"],[{"bin":"6.000000"},"139"],[{"bin":"7.000000"},"125"],[{"bin":"8.000000"},"52"],[{"bin":"9.000000"},"84"],[{"bin":"10.000000"},"61"],[{"bin":"11.000000"},"111"],[{"bin":"12.000000"},"68"],[{"bin":"13.000000"},"112"],[{"bin":"14.000000"},"61"],[{"bin":"15.000000"},"46"],[{"bin":"16.000000"},"21"],[{"bin":"17.000000"},"9"],[{"bin":"18.000000"},"12"],[{"bin":"19.000000"},"6"],[{"bin":"20.000000"},"10"],[{"bin":"21.000000"},"2"],[{"bin":"22.000000"},"16"],[{"bin":"23.000000"},"22"],[{"bin":"24.000000"},"28"],[{"bin":"25.000000"},"28"],[{"bin":"26.000000"},"8"],[{"bin":"27.000000"},"4"],[{"bin":"28.000000"},"9"],[{"bin":"29.000000"},"20"],[{"bin":"30.000000"},"7"],[{"bin":"31.000000"},"9"],[{"bin":"32.000000"},"6"],[{"bin":"33.000000"},"12"],[{"bin":"34.000000"},"2"],[{"bin":"35.000000"},"12"],[{"bin":"36.000000"},"5"],[{"bin":"37.000000"},"7"],[{"bin":"38.000000"},"10"],[{"bin":"39.000000"},"12"],[{"bin":"40.000000"},"14"],[{"bin":"41.000000"},"2"],[{"bin":"42.000000"},"7"],[{"bin":"43.000000"},"3"],[{"bin":"44.000000"},"20"],[{"bin":"45.000000"},"25"],[{"bin":"46.000000"},"7"],[{"bin":"47.000000"},"11"],[{"bin":"48.000000"},"2"],[{"bin":"49.000000"},"8"],[{"bin":"50.000000"},"7"],[{"bin":"51.000000"},"7"],[{"bin":"52.000000"},"8"],[{"bin":"53.000000"},"7"],[{"bin":"54.000000"},"21"],[{"bin":"55.000000"},"61"],[{"bin":"56.000000"},"60"],[{"bin":"57.000000"},"45"],[{"bin":"58.000000"},"69"],[{"bin":"59.000000"},"51"],[{"bin":"60.000000"},"49"],[{"bin":"61.000000"},"39"],[{"bin":"62.000000"},"40"],[{"bin":"63.000000"},"26"],[{"bin":"64.000000"},"18"],[{"bin":"65.000000"},"9"],[{"bin":"66.000000"},"2"],[{"bin":"68.000000"},"1"],[{"bin":"69.000000"},"1"],[{"bin":"70.000000"},"1"],[{"bin":"73.000000"},"1"]],"y":[[{"bin":"0.000000"},"559"],[{"bin":"1.000000"},"3"],[{"bin":"2.000000"},"25"],[{"bin":"3.000000"},"68"],[{"bin":"4.000000"},"92"],[{"bin":"5.000000"},"108"],[{"bin":"6.000000"},"89"],[{"bin":"7.000000"},"132"],[{"bin":"8.000000"},"61"],[{"bin":"9.000000"},"141"],[{"bin":"10.000000"},"95"],[{"bin":"11.000000"},"201"],[{"bin":"12.000000"},"251"],[{"bin":"13.000000"},"287"],[{"bin":"14.000000"},"175"],[{"bin":"15.000000"},"174"],[{"bin":"16.000000"},"93"],[{"bin":"17.000000"},"38"],[{"bin":"18.000000"},"32"],[{"bin":"19.000000"},"16"],[{"bin":"20.000000"},"28"],[{"bin":"21.000000"},"15"],[{"bin":"22.000000"},"18"],[{"bin":"23.000000"},"12"],[{"bin":"24.000000"},"37"],[{"bin":"25.000000"},"30"],[{"bin":"26.000000"},"7"],[{"bin":"27.000000"},"9"],[{"bin":"28.000000"},"7"],[{"bin":"29.000000"},"12"],[{"bin":"30.000000"},"11"],[{"bin":"31.000000"},"7"],[{"bin":"32.000000"},"12"],[{"bin":"33.000000"},"42"],[{"bin":"34.000000"},"11"],[{"bin":"35.000000"},"24"],[{"bin":"36.000000"},"5"],[{"bin":"37.000000"},"9"],[{"bin":"38.000000"},"25"],[{"bin":"39.000000"},"11"],[{"bin":"40.000000"},"8"],[{"bin":"41.000000"},"2"],[{"bin":"42.000000"},"9"],[{"bin":"43.000000"},"3"],[{"bin":"44.000000"},"11"],[{"bin":"45.000000"},"11"],[{"bin":"46.000000"},"5"],[{"bin":"47.000000"},"11"],[{"bin":"48.000000"},"12"],[{"bin":"49.000000"},"12"],[{"bin":"50.000000"},"5"],[{"bin":"51.000000"},"19"],[{"bin":"52.000000"},"20"],[{"bin":"53.000000"},"11"],[{"bin":"54.000000"},"7"],[{"bin":"55.000000"},"8"],[{"bin":"56.000000"},"9"],[{"bin":"57.000000"},"4"],[{"bin":"58.000000"},"6"],[{"bin":"59.000000"},"6"],[{"bin":"60.000000"},"9"],[{"bin":"61.000000"},"5"],[{"bin":"62.000000"},"24"],[{"bin":"63.000000"},"40"],[{"bin":"64.000000"},"65"],[{"bin":"65.000000"},"81"],[{"bin":"66.000000"},"49"],[{"bin":"67.000000"},"37"],[{"bin":"68.000000"},"48"],[{"bin":"69.000000"},"51"],[{"bin":"70.000000"},"37"],[{"bin":"71.000000"},"29"],[{"bin":"72.000000"},"11"],[{"bin":"73.000000"},"8"],[{"bin":"74.000000"},"1"],[{"bin":"75.000000"},"2"],[{"bin":"76.000000"},"2"]]},"hsv":{"h":[[{"bin":"0.000000"},"3"],[{"bin":"1.000000"},"3"],[{"bin":"2.000000"},"5"],[{"bin":"3.000000"},"7"],[{"bin":"4.000000"},"32"],[{"bin":"5.000000"},"50"],[{"bin":"6.000000"},"119"],[{"bin":"7.000000"},"109"],[{"bin":"8.000000"},"231"],[{"bin":"9.000000"},"70"],[{"bin":"10.000000"},"32"],[{"bin":"11.000000"},"25"],[{"bin":"12.000000"},"16"],[{"bin":"13.000000"},"18"],[{"bin":"14.000000"},"14"],[{"bin":"15.000000"},"48"],[{"bin":"16.000000"},"53"],[{"bin":"17.000000"},"17"],[{"bin":"18.000000"},"8"],[{"bin":"19.000000"},"20"],[{"bin":"20.000000"},"28"],[{"bin":"21.000000"},"8"],[{"bin":"22.000000"},"18"],[{"bin":"23.000000"},"11"],[{"bin":"24.000000"},"13"],[{"bin":"25.000000"},"17"],[{"bin":"26.000000"},"16"],[{"bin":"27.000000"},"21"],[{"bin":"28.000000"},"36"],[{"bin":"29.000000"},"12"],[{"bin":"30.000000"},"38"],[{"bin":"31.000000"},"20"],[{"bin":"32.000000"},"29"],[{"bin":"33.000000"},"60"],[{"bin":"34.000000"},"45"],[{"bin":"35.000000"},"70"],[{"bin":"36.000000"},"70"],[{"bin":"37.000000"},"126"],[{"bin":"38.000000"},"113"],[{"bin":"39.000000"},"123"],[{"bin":"40.000000"},"113"],[{"bin":"41.000000"},"101"],[{"bin":"42.000000"},"112"],[{"bin":"43.000000"},"114"],[{"bin":"44.000000"},"101"],[{"bin":"45.000000"},"104"],[{"bin":"46.000000"},"115"],[{"bin":"47.000000"},"64"],[{"bin":"48.000000"},"96"],[{"bin":"49.000000"},"59"],[{"bin":"50.000000"},"49"],[{"bin":"51.000000"},"51"],[{"bin":"52.000000"},"17"],[{"bin":"53.000000"},"24"],[{"bin":"54.000000"},"17"],[{"bin":"55.000000"},"14"],[{"bin":"56.000000"},"13"],[{"bin":"57.000000"},"11"],[{"bin":"58.000000"},"8"],[{"bin":"60.000000"},"28"],[{"bin":"62.000000"},"5"],[{"bin":"63.000000"},"1"],[{"bin":"64.000000"},"7"],[{"bin":"65.000000"},"5"],[{"bin":"66.000000"},"5"],[{"bin":"67.000000"},"6"],[{"bin":"68.000000"},"1"],[{"bin":"69.000000"},"5"],[{"bin":"70.000000"},"3"],[{"bin":"71.000000"},"2"],[{"bin":"72.000000"},"6"],[{"bin":"73.000000"},"3"],[{"bin":"74.000000"},"1"],[{"bin":"75.000000"},"4"],[{"bin":"76.000000"},"1"],[{"bin":"77.000000"},"3"],[{"bin":"78.000000"},"2"],[{"bin":"79.000000"},"1"],[{"bin":"80.000000"},"3"],[{"bin":"82.000000"},"1"],[{"bin":"83.000000"},"3"],[{"bin":"85.000000"},"2"],[{"bin":"86.000000"},"2"],[{"bin":"87.000000"},"1"],[{"bin":"88.000000"},"1"],[{"bin":"89.000000"},"1"],[{"bin":"90.000000"},"2"],[{"bin":"93.000000"},"2"],[{"bin":"94.000000"},"2"],[{"bin":"95.000000"},"2"],[{"bin":"97.000000"},"1"],[{"bin":"98.000000"},"1"],[{"bin":"100.000000"},"2"],[{"bin":"107.000000"},"1"],[{"bin":"108.000000"},"1"],[{"bin":"111.000000"},"6"],[{"bin":"113.000000"},"1"],[{"bin":"120.000000"},"2"],[{"bin":"123.000000"},"1"],[{"bin":"124.000000"},"1"],[{"bin":"127.000000"},"1"],[{"bin":"132.000000"},"2"],[{"bin":"137.000000"},"3"],[{"bin":"146.000000"},"1"],[{"bin":"147.000000"},"1"],[{"bin":"152.000000"},"1"],[{"bin":"154.000000"},"1"],[{"bin":"158.000000"},"1"],[{"bin":"169.000000"},"1"],[{"bin":"175.000000"},"1"],[{"bin":"183.000000"},"1"],[{"bin":"185.000000"},"1"],[{"bin":"189.000000"},"2"],[{"bin":"190.000000"},"2"],[{"bin":"191.000000"},"1"],[{"bin":"193.000000"},"1"],[{"bin":"194.000000"},"3"],[{"bin":"195.000000"},"1"],[{"bin":"196.000000"},"2"],[{"bin":"197.000000"},"1"],[{"bin":"198.000000"},"2"],[{"bin":"199.000000"},"2"],[{"bin":"200.000000"},"3"],[{"bin":"201.000000"},"7"],[{"bin":"202.000000"},"13"],[{"bin":"203.000000"},"30"],[{"bin":"204.000000"},"47"],[{"bin":"205.000000"},"78"],[{"bin":"206.000000"},"118"],[{"bin":"207.000000"},"68"],[{"bin":"208.000000"},"59"],[{"bin":"209.000000"},"40"],[{"bin":"210.000000"},"28"],[{"bin":"211.000000"},"20"],[{"bin":"212.000000"},"10"],[{"bin":"213.000000"},"6"],[{"bin":"214.000000"},"2"],[{"bin":"215.000000"},"3"],[{"bin":"216.000000"},"1"],[{"bin":"223.000000"},"1"],[{"bin":"237.000000"},"1"],[{"bin":"258.000000"},"1"],[{"bin":"270.000000"},"1"],[{"bin":"303.000000"},"1"],[{"bin":"310.000000"},"1"],[{"bin":"320.000000"},"2"],[{"bin":"328.000000"},"1"],[{"bin":"349.000000"},"1"],[{"bin":"351.000000"},"1"],[{"bin":"355.000000"},"1"],[{"bin":"356.000000"},"1"],[{"bin":"358.000000"},"1"],[{"bin":"359.000000"},"4"],[{"bin":"360.000000"},"2"]],"s":[[{"bin":"0.000000"},"1"],[{"bin":"3.000000"},"8"],[{"bin":"4.000000"},"21"],[{"bin":"5.000000"},"10"],[{"bin":"6.000000"},"8"],[{"bin":"7.000000"},"13"],[{"bin":"8.000000"},"27"],[{"bin":"9.000000"},"34"],[{"bin":"10.000000"},"97"],[{"bin":"11.000000"},"171"],[{"bin":"12.000000"},"212"],[{"bin":"13.000000"},"370"],[{"bin":"14.000000"},"362"],[{"bin":"15.000000"},"255"],[{"bin":"16.000000"},"195"],[{"bin":"17.000000"},"136"],[{"bin":"18.000000"},"86"],[{"bin":"19.000000"},"36"],[{"bin":"20.000000"},"26"],[{"bin":"21.000000"},"24"],[{"bin":"22.000000"},"16"],[{"bin":"23.000000"},"17"],[{"bin":"24.000000"},"19"],[{"bin":"25.000000"},"26"],[{"bin":"26.000000"},"46"],[{"bin":"27.000000"},"20"],[{"bin":"28.000000"},"8"],[{"bin":"29.000000"},"12"],[{"bin":"30.000000"},"14"],[{"bin":"31.000000"},"9"],[{"bin":"32.000000"},"14"],[{"bin":"33.000000"},"10"],[{"bin":"34.000000"},"13"],[{"bin":"35.000000"},"17"],[{"bin":"36.000000"},"35"],[{"bin":"37.000000"},"15"],[{"bin":"38.000000"},"25"],[{"bin":"39.000000"},"13"],[{"bin":"40.000000"},"19"],[{"bin":"41.000000"},"29"],[{"bin":"42.000000"},"26"],[{"bin":"43.000000"},"13"],[{"bin":"44.000000"},"16"],[{"bin":"45.000000"},"15"],[{"bin":"46.000000"},"22"],[{"bin":"47.000000"},"15"],[{"bin":"48.000000"},"27"],[{"bin":"49.000000"},"17"],[{"bin":"50.000000"},"28"],[{"bin":"51.000000"},"34"],[{"bin":"52.000000"},"31"],[{"bin":"53.000000"},"53"],[{"bin":"54.000000"},"38"],[{"bin":"55.000000"},"45"],[{"bin":"56.000000"},"43"],[{"bin":"57.000000"},"50"],[{"bin":"58.000000"},"36"],[{"bin":"59.000000"},"11"],[{"bin":"60.000000"},"13"],[{"bin":"61.000000"},"13"],[{"bin":"62.000000"},"7"],[{"bin":"63.000000"},"14"],[{"bin":"64.000000"},"13"],[{"bin":"65.000000"},"5"],[{"bin":"66.000000"},"5"],[{"bin":"67.000000"},"4"],[{"bin":"68.000000"},"1"],[{"bin":"69.000000"},"7"],[{"bin":"70.000000"},"8"],[{"bin":"71.000000"},"5"],[{"bin":"72.000000"},"8"],[{"bin":"73.000000"},"40"],[{"bin":"74.000000"},"46"],[{"bin":"75.000000"},"60"],[{"bin":"76.000000"},"48"],[{"bin":"77.000000"},"46"],[{"bin":"78.000000"},"36"],[{"bin":"79.000000"},"69"],[{"bin":"80.000000"},"43"],[{"bin":"81.000000"},"37"],[{"bin":"82.000000"},"57"],[{"bin":"83.000000"},"30"],[{"bin":"84.000000"},"18"],[{"bin":"85.000000"},"11"],[{"bin":"86.000000"},"8"],[{"bin":"87.000000"},"3"],[{"bin":"88.000000"},"2"],[{"bin":"89.000000"},"2"],[{"bin":"91.000000"},"1"],[{"bin":"93.000000"},"1"]],"v":[[{"bin":"8.000000"},"1"],[{"bin":"12.000000"},"1"],[{"bin":"15.000000"},"4"],[{"bin":"16.000000"},"4"],[{"bin":"17.000000"},"2"],[{"bin":"18.000000"},"1"],[{"bin":"19.000000"},"1"],[{"bin":"20.000000"},"3"],[{"bin":"21.000000"},"3"],[{"bin":"22.000000"},"7"],[{"bin":"23.000000"},"8"],[{"bin":"24.000000"},"9"],[{"bin":"25.000000"},"12"],[{"bin":"26.000000"},"8"],[{"bin":"27.000000"},"11"],[{"bin":"28.000000"},"12"],[{"bin":"29.000000"},"15"],[{"bin":"30.000000"},"9"],[{"bin":"31.000000"},"16"],[{"bin":"32.000000"},"12"],[{"bin":"33.000000"},"14"],[{"bin":"34.000000"},"15"],[{"bin":"35.000000"},"12"],[{"bin":"36.000000"},"18"],[{"bin":"37.000000"},"13"],[{"bin":"38.000000"},"27"],[{"bin":"39.000000"},"18"],[{"bin":"40.000000"},"29"],[{"bin":"41.000000"},"20"],[{"bin":"42.000000"},"32"],[{"bin":"43.000000"},"12"],[{"bin":"44.000000"},"20"],[{"bin":"45.000000"},"24"],[{"bin":"46.000000"},"16"],[{"bin":"47.000000"},"26"],[{"bin":"48.000000"},"27"],[{"bin":"49.000000"},"57"],[{"bin":"50.000000"},"36"],[{"bin":"51.000000"},"74"],[{"bin":"52.000000"},"54"],[{"bin":"53.000000"},"84"],[{"bin":"54.000000"},"34"],[{"bin":"55.000000"},"58"],[{"bin":"56.000000"},"59"],[{"bin":"57.000000"},"33"],[{"bin":"58.000000"},"49"],[{"bin":"59.000000"},"36"],[{"bin":"60.000000"},"36"],[{"bin":"61.000000"},"25"],[{"bin":"62.000000"},"32"],[{"bin":"63.000000"},"18"],[{"bin":"64.000000"},"27"],[{"bin":"65.000000"},"22"],[{"bin":"66.000000"},"18"],[{"bin":"67.000000"},"23"],[{"bin":"68.000000"},"15"],[{"bin":"69.000000"},"20"],[{"bin":"70.000000"},"21"],[{"bin":"71.000000"},"31"],[{"bin":"72.000000"},"38"],[{"bin":"73.000000"},"30"],[{"bin":"74.000000"},"16"],[{"bin":"75.000000"},"25"],[{"bin":"76.000000"},"22"],[{"bin":"77.000000"},"23"],[{"bin":"78.000000"},"44"],[{"bin":"79.000000"},"35"],[{"bin":"80.000000"},"36"],[{"bin":"81.000000"},"22"],[{"bin":"82.000000"},"27"],[{"bin":"83.000000"},"35"],[{"bin":"84.000000"},"130"],[{"bin":"85.000000"},"199"],[{"bin":"86.000000"},"183"],[{"bin":"87.000000"},"181"],[{"bin":"88.000000"},"83"],[{"bin":"89.000000"},"91"],[{"bin":"90.000000"},"56"],[{"bin":"91.000000"},"111"],[{"bin":"92.000000"},"63"],[{"bin":"93.000000"},"101"],[{"bin":"94.000000"},"57"],[{"bin":"95.000000"},"169"],[{"bin":"96.000000"},"200"],[{"bin":"97.000000"},"126"],[{"bin":"98.000000"},"135"],[{"bin":"99.000000"},"50"],[{"bin":"100.000000"},"38"]]},"lab":{"a":[[{"bin":"-14.000000"},"2"],[{"bin":"-11.000000"},"1"],[{"bin":"-9.000000"},"7"],[{"bin":"-8.000000"},"13"],[{"bin":"-7.000000"},"27"],[{"bin":"-6.000000"},"66"],[{"bin":"-5.000000"},"185"],[{"bin":"-4.000000"},"168"],[{"bin":"-3.000000"},"227"],[{"bin":"-2.000000"},"348"],[{"bin":"-1.000000"},"473"],[{"bin":"0.000000"},"482"],[{"bin":"1.000000"},"360"],[{"bin":"2.000000"},"171"],[{"bin":"3.000000"},"58"],[{"bin":"4.000000"},"34"],[{"bin":"5.000000"},"18"],[{"bin":"6.000000"},"29"],[{"bin":"7.000000"},"24"],[{"bin":"8.000000"},"32"],[{"bin":"9.000000"},"13"],[{"bin":"10.000000"},"21"],[{"bin":"11.000000"},"5"],[{"bin":"12.000000"},"6"],[{"bin":"13.000000"},"12"],[{"bin":"14.000000"},"5"],[{"bin":"15.000000"},"8"],[{"bin":"16.000000"},"8"],[{"bin":"17.000000"},"12"],[{"bin":"18.000000"},"20"],[{"bin":"19.000000"},"24"],[{"bin":"20.000000"},"20"],[{"bin":"21.000000"},"15"],[{"bin":"22.000000"},"8"],[{"bin":"23.000000"},"10"],[{"bin":"24.000000"},"16"],[{"bin":"25.000000"},"10"],[{"bin":"26.000000"},"3"],[{"bin":"27.000000"},"5"],[{"bin":"28.000000"},"4"],[{"bin":"29.000000"},"3"],[{"bin":"30.000000"},"2"],[{"bin":"31.000000"},"9"],[{"bin":"32.000000"},"5"],[{"bin":"33.000000"},"9"],[{"bin":"34.000000"},"6"],[{"bin":"35.000000"},"12"],[{"bin":"36.000000"},"16"],[{"bin":"37.000000"},"8"],[{"bin":"38.000000"},"3"],[{"bin":"39.000000"},"6"],[{"bin":"40.000000"},"7"],[{"bin":"41.000000"},"10"],[{"bin":"42.000000"},"18"],[{"bin":"43.000000"},"25"],[{"bin":"44.000000"},"3"],[{"bin":"45.000000"},"10"],[{"bin":"46.000000"},"6"],[{"bin":"47.000000"},"10"],[{"bin":"48.000000"},"5"],[{"bin":"49.000000"},"6"],[{"bin":"50.000000"},"6"],[{"bin":"51.000000"},"8"],[{"bin":"52.000000"},"11"],[{"bin":"53.000000"},"31"],[{"bin":"54.000000"},"62"],[{"bin":"55.000000"},"58"],[{"bin":"56.000000"},"63"],[{"bin":"57.000000"},"74"],[{"bin":"58.000000"},"46"],[{"bin":"59.000000"},"61"],[{"bin":"60.000000"},"41"],[{"bin":"61.000000"},"37"],[{"bin":"62.000000"},"12"],[{"bin":"63.000000"},"7"],[{"bin":"65.000000"},"2"],[{"bin":"66.000000"},"1"],[{"bin":"68.000000"},"1"]],"b":[[{"bin":"-34.000000"},"1"],[{"bin":"-33.000000"},"1"],[{"bin":"-30.000000"},"1"],[{"bin":"-29.000000"},"2"],[{"bin":"-28.000000"},"5"],[{"bin":"-27.000000"},"6"],[{"bin":"-26.000000"},"9"],[{"bin":"-25.000000"},"24"],[{"bin":"-24.000000"},"37"],[{"bin":"-23.000000"},"43"],[{"bin":"-22.000000"},"43"],[{"bin":"-21.000000"},"39"],[{"bin":"-20.000000"},"48"],[{"bin":"-19.000000"},"56"],[{"bin":"-18.000000"},"40"],[{"bin":"-17.000000"},"32"],[{"bin":"-16.000000"},"25"],[{"bin":"-15.000000"},"22"],[{"bin":"-14.000000"},"23"],[{"bin":"-13.000000"},"19"],[{"bin":"-12.000000"},"14"],[{"bin":"-11.000000"},"19"],[{"bin":"-10.000000"},"11"],[{"bin":"-9.000000"},"13"],[{"bin":"-8.000000"},"6"],[{"bin":"-7.000000"},"5"],[{"bin":"-6.000000"},"4"],[{"bin":"-5.000000"},"2"],[{"bin":"-4.000000"},"3"],[{"bin":"-3.000000"},"6"],[{"bin":"-2.000000"},"2"],[{"bin":"-1.000000"},"2"],[{"bin":"0.000000"},"1"],[{"bin":"1.000000"},"8"],[{"bin":"2.000000"},"21"],[{"bin":"3.000000"},"63"],[{"bin":"4.000000"},"72"],[{"bin":"5.000000"},"66"],[{"bin":"6.000000"},"88"],[{"bin":"7.000000"},"131"],[{"bin":"8.000000"},"111"],[{"bin":"9.000000"},"122"],[{"bin":"10.000000"},"160"],[{"bin":"11.000000"},"272"],[{"bin":"12.000000"},"285"],[{"bin":"13.000000"},"259"],[{"bin":"14.000000"},"219"],[{"bin":"15.000000"},"140"],[{"bin":"16.000000"},"68"],[{"bin":"17.000000"},"47"],[{"bin":"18.000000"},"59"],[{"bin":"19.000000"},"52"],[{"bin":"20.000000"},"48"],[{"bin":"21.000000"},"28"],[{"bin":"22.000000"},"13"],[{"bin":"23.000000"},"25"],[{"bin":"24.000000"},"36"],[{"bin":"25.000000"},"9"],[{"bin":"26.000000"},"14"],[{"bin":"27.000000"},"8"],[{"bin":"28.000000"},"11"],[{"bin":"29.000000"},"23"],[{"bin":"30.000000"},"35"],[{"bin":"31.000000"},"17"],[{"bin":"32.000000"},"9"],[{"bin":"33.000000"},"16"],[{"bin":"34.000000"},"12"],[{"bin":"35.000000"},"8"],[{"bin":"36.000000"},"10"],[{"bin":"37.000000"},"5"],[{"bin":"38.000000"},"11"],[{"bin":"39.000000"},"11"],[{"bin":"40.000000"},"18"],[{"bin":"41.000000"},"59"],[{"bin":"42.000000"},"56"],[{"bin":"43.000000"},"63"],[{"bin":"44.000000"},"58"],[{"bin":"45.000000"},"51"],[{"bin":"46.000000"},"52"],[{"bin":"47.000000"},"37"],[{"bin":"48.000000"},"52"],[{"bin":"49.000000"},"32"],[{"bin":"50.000000"},"8"],[{"bin":"51.000000"},"4"],[{"bin":"52.000000"},"3"],[{"bin":"53.000000"},"1"]],"l":[[{"bin":"6.000000"},"1"],[{"bin":"11.000000"},"1"],[{"bin":"13.000000"},"1"],[{"bin":"14.000000"},"2"],[{"bin":"15.000000"},"6"],[{"bin":"16.000000"},"2"],[{"bin":"17.000000"},"3"],[{"bin":"18.000000"},"4"],[{"bin":"19.000000"},"6"],[{"bin":"20.000000"},"4"],[{"bin":"21.000000"},"5"],[{"bin":"22.000000"},"12"],[{"bin":"23.000000"},"15"],[{"bin":"24.000000"},"8"],[{"bin":"25.000000"},"14"],[{"bin":"26.000000"},"7"],[{"bin":"27.000000"},"16"],[{"bin":"28.000000"},"18"],[{"bin":"29.000000"},"19"],[{"bin":"30.000000"},"19"],[{"bin":"31.000000"},"24"],[{"bin":"32.000000"},"20"],[{"bin":"33.000000"},"33"],[{"bin":"34.000000"},"27"],[{"bin":"35.000000"},"32"],[{"bin":"36.000000"},"26"],[{"bin":"37.000000"},"29"],[{"bin":"38.000000"},"35"],[{"bin":"39.000000"},"56"],[{"bin":"40.000000"},"71"],[{"bin":"41.000000"},"74"],[{"bin":"42.000000"},"77"],[{"bin":"43.000000"},"51"],[{"bin":"44.000000"},"48"],[{"bin":"45.000000"},"25"],[{"bin":"46.000000"},"29"],[{"bin":"47.000000"},"25"],[{"bin":"48.000000"},"40"],[{"bin":"49.000000"},"62"],[{"bin":"50.000000"},"134"],[{"bin":"51.000000"},"117"],[{"bin":"52.000000"},"133"],[{"bin":"53.000000"},"92"],[{"bin":"54.000000"},"30"],[{"bin":"55.000000"},"25"],[{"bin":"56.000000"},"27"],[{"bin":"57.000000"},"25"],[{"bin":"58.000000"},"52"],[{"bin":"59.000000"},"36"],[{"bin":"60.000000"},"30"],[{"bin":"61.000000"},"35"],[{"bin":"62.000000"},"62"],[{"bin":"63.000000"},"21"],[{"bin":"64.000000"},"18"],[{"bin":"65.000000"},"27"],[{"bin":"66.000000"},"28"],[{"bin":"67.000000"},"22"],[{"bin":"68.000000"},"31"],[{"bin":"69.000000"},"20"],[{"bin":"70.000000"},"19"],[{"bin":"71.000000"},"26"],[{"bin":"72.000000"},"36"],[{"bin":"73.000000"},"49"],[{"bin":"74.000000"},"43"],[{"bin":"75.000000"},"71"],[{"bin":"76.000000"},"34"],[{"bin":"77.000000"},"29"],[{"bin":"78.000000"},"31"],[{"bin":"79.000000"},"41"],[{"bin":"80.000000"},"45"],[{"bin":"81.000000"},"35"],[{"bin":"82.000000"},"40"],[{"bin":"83.000000"},"28"],[{"bin":"84.000000"},"64"],[{"bin":"85.000000"},"84"],[{"bin":"86.000000"},"109"],[{"bin":"87.000000"},"102"],[{"bin":"88.000000"},"57"],[{"bin":"89.000000"},"59"],[{"bin":"90.000000"},"70"],[{"bin":"91.000000"},"78"],[{"bin":"92.000000"},"93"],[{"bin":"93.000000"},"169"],[{"bin":"94.000000"},"153"],[{"bin":"95.000000"},"98"],[{"bin":"96.000000"},"45"],[{"bin":"97.000000"},"24"],[{"bin":"98.000000"},"6"]]},"lch":{"c":[[{"bin":"0.000000"},"1"],[{"bin":"2.000000"},"11"],[{"bin":"3.000000"},"40"],[{"bin":"4.000000"},"84"],[{"bin":"5.000000"},"77"],[{"bin":"6.000000"},"84"],[{"bin":"7.000000"},"142"],[{"bin":"8.000000"},"108"],[{"bin":"9.000000"},"118"],[{"bin":"10.000000"},"160"],[{"bin":"11.000000"},"293"],[{"bin":"12.000000"},"306"],[{"bin":"13.000000"},"276"],[{"bin":"14.000000"},"237"],[{"bin":"15.000000"},"151"],[{"bin":"16.000000"},"102"],[{"bin":"17.000000"},"72"],[{"bin":"18.000000"},"78"],[{"bin":"19.000000"},"82"],[{"bin":"20.000000"},"102"],[{"bin":"21.000000"},"55"],[{"bin":"22.000000"},"55"],[{"bin":"23.000000"},"60"],[{"bin":"24.000000"},"46"],[{"bin":"25.000000"},"44"],[{"bin":"26.000000"},"21"],[{"bin":"27.000000"},"15"],[{"bin":"28.000000"},"26"],[{"bin":"29.000000"},"32"],[{"bin":"30.000000"},"20"],[{"bin":"31.000000"},"5"],[{"bin":"32.000000"},"1"],[{"bin":"33.000000"},"9"],[{"bin":"34.000000"},"25"],[{"bin":"35.000000"},"3"],[{"bin":"36.000000"},"5"],[{"bin":"37.000000"},"3"],[{"bin":"38.000000"},"4"],[{"bin":"39.000000"},"5"],[{"bin":"40.000000"},"4"],[{"bin":"41.000000"},"8"],[{"bin":"42.000000"},"8"],[{"bin":"43.000000"},"6"],[{"bin":"44.000000"},"6"],[{"bin":"45.000000"},"4"],[{"bin":"46.000000"},"13"],[{"bin":"47.000000"},"13"],[{"bin":"48.000000"},"9"],[{"bin":"49.000000"},"3"],[{"bin":"50.000000"},"1"],[{"bin":"51.000000"},"11"],[{"bin":"52.000000"},"16"],[{"bin":"53.000000"},"23"],[{"bin":"54.000000"},"6"],[{"bin":"55.000000"},"3"],[{"bin":"56.000000"},"8"],[{"bin":"57.000000"},"8"],[{"bin":"58.000000"},"3"],[{"bin":"59.000000"},"9"],[{"bin":"60.000000"},"5"],[{"bin":"61.000000"},"2"],[{"bin":"62.000000"},"7"],[{"bin":"63.000000"},"2"],[{"bin":"64.000000"},"7"],[{"bin":"65.000000"},"5"],[{"bin":"66.000000"},"6"],[{"bin":"67.000000"},"28"],[{"bin":"68.000000"},"53"],[{"bin":"69.000000"},"33"],[{"bin":"70.000000"},"62"],[{"bin":"71.000000"},"55"],[{"bin":"72.000000"},"36"],[{"bin":"73.000000"},"29"],[{"bin":"74.000000"},"29"],[{"bin":"75.000000"},"60"],[{"bin":"76.000000"},"41"],[{"bin":"77.000000"},"31"],[{"bin":"78.000000"},"21"],[{"bin":"79.000000"},"11"],[{"bin":"80.000000"},"3"],[{"bin":"83.000000"},"2"],[{"bin":"84.000000"},"1"],[{"bin":"85.000000"},"1"]],"h":[[{"bin":"6.000000"},"1"],[{"bin":"11.000000"},"1"],[{"bin":"14.000000"},"1"],[{"bin":"15.000000"},"1"],[{"bin":"19.000000"},"1"],[{"bin":"20.000000"},"1"],[{"bin":"28.000000"},"1"],[{"bin":"29.000000"},"2"],[{"bin":"30.000000"},"9"],[{"bin":"31.000000"},"5"],[{"bin":"32.000000"},"7"],[{"bin":"33.000000"},"13"],[{"bin":"34.000000"},"17"],[{"bin":"35.000000"},"38"],[{"bin":"36.000000"},"85"],[{"bin":"37.000000"},"120"],[{"bin":"38.000000"},"189"],[{"bin":"39.000000"},"142"],[{"bin":"40.000000"},"54"],[{"bin":"41.000000"},"26"],[{"bin":"42.000000"},"13"],[{"bin":"43.000000"},"13"],[{"bin":"44.000000"},"37"],[{"bin":"45.000000"},"25"],[{"bin":"46.000000"},"32"],[{"bin":"47.000000"},"19"],[{"bin":"48.000000"},"5"],[{"bin":"49.000000"},"7"],[{"bin":"50.000000"},"5"],[{"bin":"51.000000"},"9"],[{"bin":"52.000000"},"15"],[{"bin":"53.000000"},"16"],[{"bin":"54.000000"},"6"],[{"bin":"55.000000"},"6"],[{"bin":"56.000000"},"2"],[{"bin":"57.000000"},"11"],[{"bin":"58.000000"},"2"],[{"bin":"59.000000"},"9"],[{"bin":"60.000000"},"8"],[{"bin":"61.000000"},"5"],[{"bin":"62.000000"},"5"],[{"bin":"63.000000"},"8"],[{"bin":"64.000000"},"11"],[{"bin":"65.000000"},"10"],[{"bin":"66.000000"},"8"],[{"bin":"67.000000"},"13"],[{"bin":"68.000000"},"21"],[{"bin":"69.000000"},"17"],[{"bin":"70.000000"},"6"],[{"bin":"71.000000"},"15"],[{"bin":"72.000000"},"5"],[{"bin":"73.000000"},"7"],[{"bin":"74.000000"},"26"],[{"bin":"75.000000"},"10"],[{"bin":"76.000000"},"14"],[{"bin":"77.000000"},"18"],[{"bin":"78.000000"},"18"],[{"bin":"79.000000"},"46"],[{"bin":"80.000000"},"28"],[{"bin":"81.000000"},"36"],[{"bin":"82.000000"},"35"],[{"bin":"83.000000"},"45"],[{"bin":"84.000000"},"69"],[{"bin":"85.000000"},"68"],[{"bin":"86.000000"},"81"],[{"bin":"87.000000"},"94"],[{"bin":"88.000000"},"93"],[{"bin":"89.000000"},"75"],[{"bin":"90.000000"},"80"],[{"bin":"91.000000"},"80"],[{"bin":"92.000000"},"74"],[{"bin":"93.000000"},"98"],[{"bin":"94.000000"},"80"],[{"bin":"95.000000"},"84"],[{"bin":"96.000000"},"99"],[{"bin":"97.000000"},"94"],[{"bin":"98.000000"},"77"],[{"bin":"99.000000"},"78"],[{"bin":"100.000000"},"64"],[{"bin":"101.000000"},"48"],[{"bin":"102.000000"},"48"],[{"bin":"103.000000"},"25"],[{"bin":"104.000000"},"28"],[{"bin":"105.000000"},"11"],[{"bin":"106.000000"},"18"],[{"bin":"107.000000"},"13"],[{"bin":"108.000000"},"7"],[{"bin":"109.000000"},"20"],[{"bin":"110.000000"},"10"],[{"bin":"111.000000"},"5"],[{"bin":"112.000000"},"8"],[{"bin":"113.000000"},"7"],[{"bin":"114.000000"},"6"],[{"bin":"115.000000"},"5"],[{"bin":"116.000000"},"7"],[{"bin":"117.000000"},"4"],[{"bin":"118.000000"},"5"],[{"bin":"119.000000"},"3"],[{"bin":"120.000000"},"3"],[{"bin":"121.000000"},"6"],[{"bin":"122.000000"},"1"],[{"bin":"123.000000"},"2"],[{"bin":"124.000000"},"4"],[{"bin":"125.000000"},"1"],[{"bin":"126.000000"},"3"],[{"bin":"127.000000"},"3"],[{"bin":"129.000000"},"2"],[{"bin":"131.000000"},"6"],[{"bin":"132.000000"},"1"],[{"bin":"133.000000"},"1"],[{"bin":"134.000000"},"1"],[{"bin":"135.000000"},"1"],[{"bin":"138.000000"},"1"],[{"bin":"139.000000"},"1"],[{"bin":"140.000000"},"6"],[{"bin":"141.000000"},"1"],[{"bin":"143.000000"},"1"],[{"bin":"144.000000"},"1"],[{"bin":"145.000000"},"2"],[{"bin":"147.000000"},"1"],[{"bin":"150.000000"},"2"],[{"bin":"154.000000"},"3"],[{"bin":"160.000000"},"1"],[{"bin":"161.000000"},"1"],[{"bin":"164.000000"},"1"],[{"bin":"167.000000"},"1"],[{"bin":"170.000000"},"1"],[{"bin":"184.000000"},"1"],[{"bin":"191.000000"},"1"],[{"bin":"204.000000"},"1"],[{"bin":"207.000000"},"1"],[{"bin":"214.000000"},"1"],[{"bin":"215.000000"},"1"],[{"bin":"216.000000"},"2"],[{"bin":"218.000000"},"1"],[{"bin":"223.000000"},"1"],[{"bin":"224.000000"},"1"],[{"bin":"226.000000"},"2"],[{"bin":"228.000000"},"3"],[{"bin":"232.000000"},"2"],[{"bin":"235.000000"},"2"],[{"bin":"239.000000"},"1"],[{"bin":"240.000000"},"2"],[{"bin":"241.000000"},"2"],[{"bin":"242.000000"},"1"],[{"bin":"243.000000"},"4"],[{"bin":"244.000000"},"7"],[{"bin":"245.000000"},"6"],[{"bin":"246.000000"},"4"],[{"bin":"247.000000"},"6"],[{"bin":"248.000000"},"9"],[{"bin":"249.000000"},"14"],[{"bin":"250.000000"},"18"],[{"bin":"251.000000"},"14"],[{"bin":"252.000000"},"19"],[{"bin":"253.000000"},"21"],[{"bin":"254.000000"},"30"],[{"bin":"255.000000"},"39"],[{"bin":"256.000000"},"37"],[{"bin":"257.000000"},"50"],[{"bin":"258.000000"},"33"],[{"bin":"259.000000"},"39"],[{"bin":"260.000000"},"18"],[{"bin":"261.000000"},"29"],[{"bin":"262.000000"},"31"],[{"bin":"263.000000"},"17"],[{"bin":"264.000000"},"20"],[{"bin":"265.000000"},"14"],[{"bin":"266.000000"},"12"],[{"bin":"267.000000"},"16"],[{"bin":"268.000000"},"7"],[{"bin":"269.000000"},"6"],[{"bin":"270.000000"},"4"],[{"bin":"273.000000"},"1"],[{"bin":"274.000000"},"1"],[{"bin":"276.000000"},"1"],[{"bin":"277.000000"},"2"],[{"bin":"290.000000"},"1"],[{"bin":"303.000000"},"1"],[{"bin":"310.000000"},"1"],[{"bin":"313.000000"},"1"],[{"bin":"327.000000"},"1"],[{"bin":"330.000000"},"1"],[{"bin":"337.000000"},"2"],[{"bin":"344.000000"},"1"]],"l":[[{"bin":"6.000000"},"1"],[{"bin":"11.000000"},"1"],[{"bin":"13.000000"},"1"],[{"bin":"14.000000"},"2"],[{"bin":"15.000000"},"6"],[{"bin":"16.000000"},"2"],[{"bin":"17.000000"},"3"],[{"bin":"18.000000"},"4"],[{"bin":"19.000000"},"6"],[{"bin":"20.000000"},"4"],[{"bin":"21.000000"},"5"],[{"bin":"22.000000"},"12"],[{"bin":"23.000000"},"15"],[{"bin":"24.000000"},"8"],[{"bin":"25.000000"},"14"],[{"bin":"26.000000"},"7"],[{"bin":"27.000000"},"16"],[{"bin":"28.000000"},"18"],[{"bin":"29.000000"},"19"],[{"bin":"30.000000"},"19"],[{"bin":"31.000000"},"24"],[{"bin":"32.000000"},"20"],[{"bin":"33.000000"},"33"],[{"bin":"34.000000"},"27"],[{"bin":"35.000000"},"32"],[{"bin":"36.000000"},"26"],[{"bin":"37.000000"},"29"],[{"bin":"38.000000"},"35"],[{"bin":"39.000000"},"56"],[{"bin":"40.000000"},"71"],[{"bin":"41.000000"},"74"],[{"bin":"42.000000"},"77"],[{"bin":"43.000000"},"51"],[{"bin":"44.000000"},"48"],[{"bin":"45.000000"},"25"],[{"bin":"46.000000"},"29"],[{"bin":"47.000000"},"25"],[{"bin":"48.000000"},"40"],[{"bin":"49.000000"},"62"],[{"bin":"50.000000"},"134"],[{"bin":"51.000000"},"117"],[{"bin":"52.000000"},"133"],[{"bin":"53.000000"},"92"],[{"bin":"54.000000"},"30"],[{"bin":"55.000000"},"25"],[{"bin":"56.000000"},"27"],[{"bin":"57.000000"},"25"],[{"bin":"58.000000"},"52"],[{"bin":"59.000000"},"36"],[{"bin":"60.000000"},"30"],[{"bin":"61.000000"},"35"],[{"bin":"62.000000"},"62"],[{"bin":"63.000000"},"21"],[{"bin":"64.000000"},"18"],[{"bin":"65.000000"},"27"],[{"bin":"66.000000"},"28"],[{"bin":"67.000000"},"22"],[{"bin":"68.000000"},"31"],[{"bin":"69.000000"},"20"],[{"bin":"70.000000"},"19"],[{"bin":"71.000000"},"26"],[{"bin":"72.000000"},"36"],[{"bin":"73.000000"},"49"],[{"bin":"74.000000"},"43"],[{"bin":"75.000000"},"71"],[{"bin":"76.000000"},"34"],[{"bin":"77.000000"},"29"],[{"bin":"78.000000"},"31"],[{"bin":"79.000000"},"41"],[{"bin":"80.000000"},"45"],[{"bin":"81.000000"},"35"],[{"bin":"82.000000"},"40"],[{"bin":"83.000000"},"28"],[{"bin":"84.000000"},"64"],[{"bin":"85.000000"},"84"],[{"bin":"86.000000"},"109"],[{"bin":"87.000000"},"102"],[{"bin":"88.000000"},"57"],[{"bin":"89.000000"},"59"],[{"bin":"90.000000"},"70"],[{"bin":"91.000000"},"78"],[{"bin":"92.000000"},"93"],[{"bin":"93.000000"},"169"],[{"bin":"94.000000"},"153"],[{"bin":"95.000000"},"98"],[{"bin":"96.000000"},"45"],[{"bin":"97.000000"},"24"],[{"bin":"98.000000"},"6"]]},"rgb":{"b":[[{"bin":"7.000000"},"1"],[{"bin":"13.000000"},"1"],[{"bin":"14.000000"},"3"],[{"bin":"15.000000"},"1"],[{"bin":"16.000000"},"3"],[{"bin":"17.000000"},"2"],[{"bin":"18.000000"},"3"],[{"bin":"19.000000"},"2"],[{"bin":"20.000000"},"3"],[{"bin":"21.000000"},"2"],[{"bin":"22.000000"},"1"],[{"bin":"23.000000"},"2"],[{"bin":"24.000000"},"3"],[{"bin":"25.000000"},"2"],[{"bin":"26.000000"},"4"],[{"bin":"27.000000"},"2"],[{"bin":"28.000000"},"6"],[{"bin":"29.000000"},"3"],[{"bin":"30.000000"},"5"],[{"bin":"31.000000"},"11"],[{"bin":"32.000000"},"8"],[{"bin":"33.000000"},"6"],[{"bin":"34.000000"},"10"],[{"bin":"35.000000"},"15"],[{"bin":"36.000000"},"15"],[{"bin":"37.000000"},"6"],[{"bin":"38.000000"},"24"],[{"bin":"39.000000"},"23"],[{"bin":"40.000000"},"19"],[{"bin":"41.000000"},"18"],[{"bin":"42.000000"},"18"],[{"bin":"43.000000"},"21"],[{"bin":"44.000000"},"23"],[{"bin":"45.000000"},"28"],[{"bin":"46.000000"},"37"],[{"bin":"47.000000"},"22"],[{"bin":"48.000000"},"19"],[{"bin":"49.000000"},"18"],[{"bin":"50.000000"},"24"],[{"bin":"51.000000"},"19"],[{"bin":"52.000000"},"21"],[{"bin":"53.000000"},"29"],[{"bin":"54.000000"},"23"],[{"bin":"55.000000"},"22"],[{"bin":"56.000000"},"30"],[{"bin":"57.000000"},"21"],[{"bin":"58.000000"},"25"],[{"bin":"59.000000"},"27"],[{"bin":"60.000000"},"14"],[{"bin":"61.000000"},"14"],[{"bin":"62.000000"},"7"],[{"bin":"63.000000"},"7"],[{"bin":"64.000000"},"10"],[{"bin":"65.000000"},"6"],[{"bin":"66.000000"},"6"],[{"bin":"67.000000"},"8"],[{"bin":"68.000000"},"4"],[{"bin":"69.000000"},"8"],[{"bin":"70.000000"},"5"],[{"bin":"71.000000"},"6"],[{"bin":"72.000000"},"6"],[{"bin":"73.000000"},"6"],[{"bin":"74.000000"},"10"],[{"bin":"75.000000"},"11"],[{"bin":"76.000000"},"9"],[{"bin":"77.000000"},"4"],[{"bin":"78.000000"},"6"],[{"bin":"79.000000"},"6"],[{"bin":"80.000000"},"11"],[{"bin":"81.000000"},"9"],[{"bin":"82.000000"},"8"],[{"bin":"83.000000"},"8"],[{"bin":"84.000000"},"14"],[{"bin":"85.000000"},"7"],[{"bin":"86.000000"},"8"],[{"bin":"87.000000"},"3"],[{"bin":"88.000000"},"3"],[{"bin":"89.000000"},"8"],[{"bin":"90.000000"},"9"],[{"bin":"91.000000"},"11"],[{"bin":"92.000000"},"10"],[{"bin":"93.000000"},"9"],[{"bin":"94.000000"},"13"],[{"bin":"95.000000"},"10"],[{"bin":"96.000000"},"12"],[{"bin":"97.000000"},"3"],[{"bin":"98.000000"},"18"],[{"bin":"99.000000"},"24"],[{"bin":"100.000000"},"18"],[{"bin":"101.000000"},"4"],[{"bin":"102.000000"},"13"],[{"bin":"103.000000"},"12"],[{"bin":"104.000000"},"9"],[{"bin":"105.000000"},"9"],[{"bin":"106.000000"},"11"],[{"bin":"107.000000"},"9"],[{"bin":"108.000000"},"6"],[{"bin":"109.000000"},"17"],[{"bin":"110.000000"},"12"],[{"bin":"111.000000"},"10"],[{"bin":"112.000000"},"6"],[{"bin":"113.000000"},"13"],[{"bin":"114.000000"},"9"],[{"bin":"115.000000"},"11"],[{"bin":"116.000000"},"15"],[{"bin":"117.000000"},"5"],[{"bin":"118.000000"},"19"],[{"bin":"119.000000"},"15"],[{"bin":"120.000000"},"12"],[{"bin":"121.000000"},"14"],[{"bin":"122.000000"},"19"],[{"bin":"123.000000"},"15"],[{"bin":"124.000000"},"17"],[{"bin":"125.000000"},"23"],[{"bin":"126.000000"},"33"],[{"bin":"127.000000"},"26"],[{"bin":"128.000000"},"28"],[{"bin":"129.000000"},"21"],[{"bin":"130.000000"},"31"],[{"bin":"131.000000"},"33"],[{"bin":"132.000000"},"34"],[{"bin":"133.000000"},"35"],[{"bin":"134.000000"},"27"],[{"bin":"135.000000"},"35"],[{"bin":"136.000000"},"36"],[{"bin":"137.000000"},"21"],[{"bin":"138.000000"},"16"],[{"bin":"139.000000"},"27"],[{"bin":"140.000000"},"21"],[{"bin":"141.000000"},"17"],[{"bin":"142.000000"},"32"],[{"bin":"143.000000"},"29"],[{"bin":"144.000000"},"17"],[{"bin":"145.000000"},"19"],[{"bin":"146.000000"},"23"],[{"bin":"147.000000"},"17"],[{"bin":"148.000000"},"20"],[{"bin":"149.000000"},"27"],[{"bin":"150.000000"},"23"],[{"bin":"151.000000"},"28"],[{"bin":"152.000000"},"14"],[{"bin":"153.000000"},"17"],[{"bin":"154.000000"},"13"],[{"bin":"155.000000"},"18"],[{"bin":"156.000000"},"16"],[{"bin":"157.000000"},"23"],[{"bin":"158.000000"},"13"],[{"bin":"159.000000"},"22"],[{"bin":"160.000000"},"14"],[{"bin":"161.000000"},"10"],[{"bin":"162.000000"},"11"],[{"bin":"163.000000"},"14"],[{"bin":"164.000000"},"12"],[{"bin":"165.000000"},"10"],[{"bin":"166.000000"},"13"],[{"bin":"167.000000"},"11"],[{"bin":"168.000000"},"6"],[{"bin":"169.000000"},"11"],[{"bin":"170.000000"},"12"],[{"bin":"171.000000"},"14"],[{"bin":"172.000000"},"15"],[{"bin":"173.000000"},"8"],[{"bin":"174.000000"},"17"],[{"bin":"175.000000"},"12"],[{"bin":"176.000000"},"14"],[{"bin":"177.000000"},"22"],[{"bin":"178.000000"},"22"],[{"bin":"179.000000"},"26"],[{"bin":"180.000000"},"15"],[{"bin":"181.000000"},"12"],[{"bin":"182.000000"},"14"],[{"bin":"183.000000"},"18"],[{"bin":"184.000000"},"19"],[{"bin":"185.000000"},"16"],[{"bin":"186.000000"},"14"],[{"bin":"187.000000"},"16"],[{"bin":"188.000000"},"27"],[{"bin":"189.000000"},"22"],[{"bin":"190.000000"},"29"],[{"bin":"191.000000"},"26"],[{"bin":"192.000000"},"37"],[{"bin":"193.000000"},"34"],[{"bin":"194.000000"},"36"],[{"bin":"195.000000"},"38"],[{"bin":"196.000000"},"38"],[{"bin":"197.000000"},"37"],[{"bin":"198.000000"},"48"],[{"bin":"199.000000"},"33"],[{"bin":"200.000000"},"33"],[{"bin":"201.000000"},"36"],[{"bin":"202.000000"},"47"],[{"bin":"203.000000"},"26"],[{"bin":"204.000000"},"31"],[{"bin":"205.000000"},"35"],[{"bin":"206.000000"},"25"],[{"bin":"207.000000"},"28"],[{"bin":"208.000000"},"41"],[{"bin":"209.000000"},"53"],[{"bin":"210.000000"},"34"],[{"bin":"211.000000"},"34"],[{"bin":"212.000000"},"27"],[{"bin":"213.000000"},"46"],[{"bin":"214.000000"},"38"],[{"bin":"215.000000"},"31"],[{"bin":"216.000000"},"36"],[{"bin":"217.000000"},"22"],[{"bin":"218.000000"},"13"],[{"bin":"219.000000"},"28"],[{"bin":"220.000000"},"9"],[{"bin":"221.000000"},"22"],[{"bin":"222.000000"},"17"],[{"bin":"223.000000"},"5"],[{"bin":"224.000000"},"6"],[{"bin":"225.000000"},"2"],[{"bin":"226.000000"},"1"],[{"bin":"227.000000"},"2"],[{"bin":"228.000000"},"2"]],"g":[[{"bin":"19.000000"},"1"],[{"bin":"22.000000"},"1"],[{"bin":"24.000000"},"1"],[{"bin":"26.000000"},"1"],[{"bin":"27.000000"},"1"],[{"bin":"28.000000"},"2"],[{"bin":"29.000000"},"2"],[{"bin":"30.000000"},"1"],[{"bin":"32.000000"},"1"],[{"bin":"34.000000"},"7"],[{"bin":"35.000000"},"4"],[{"bin":"36.000000"},"2"],[{"bin":"37.000000"},"6"],[{"bin":"38.000000"},"3"],[{"bin":"39.000000"},"2"],[{"bin":"40.000000"},"6"],[{"bin":"41.000000"},"2"],[{"bin":"42.000000"},"4"],[{"bin":"43.000000"},"4"],[{"bin":"44.000000"},"9"],[{"bin":"45.000000"},"4"],[{"bin":"46.000000"},"5"],[{"bin":"47.000000"},"6"],[{"bin":"48.000000"},"9"],[{"bin":"49.000000"},"3"],[{"bin":"50.000000"},"5"],[{"bin":"51.000000"},"11"],[{"bin":"52.000000"},"13"],[{"bin":"53.000000"},"10"],[{"bin":"54.000000"},"13"],[{"bin":"55.000000"},"12"],[{"bin":"56.000000"},"12"],[{"bin":"57.000000"},"10"],[{"bin":"58.000000"},"25"],[{"bin":"59.000000"},"21"],[{"bin":"60.000000"},"25"],[{"bin":"61.000000"},"17"],[{"bin":"62.000000"},"35"],[{"bin":"63.000000"},"36"],[{"bin":"64.000000"},"27"],[{"bin":"65.000000"},"25"],[{"bin":"66.000000"},"29"],[{"bin":"67.000000"},"29"],[{"bin":"68.000000"},"24"],[{"bin":"69.000000"},"20"],[{"bin":"70.000000"},"19"],[{"bin":"71.000000"},"28"],[{"bin":"72.000000"},"27"],[{"bin":"73.000000"},"31"],[{"bin":"74.000000"},"30"],[{"bin":"75.000000"},"24"],[{"bin":"76.000000"},"28"],[{"bin":"77.000000"},"45"],[{"bin":"78.000000"},"21"],[{"bin":"79.000000"},"28"],[{"bin":"80.000000"},"29"],[{"bin":"81.000000"},"21"],[{"bin":"82.000000"},"13"],[{"bin":"83.000000"},"14"],[{"bin":"84.000000"},"14"],[{"bin":"85.000000"},"9"],[{"bin":"86.000000"},"4"],[{"bin":"87.000000"},"8"],[{"bin":"88.000000"},"9"],[{"bin":"89.000000"},"12"],[{"bin":"90.000000"},"8"],[{"bin":"91.000000"},"9"],[{"bin":"92.000000"},"18"],[{"bin":"93.000000"},"10"],[{"bin":"94.000000"},"17"],[{"bin":"95.000000"},"25"],[{"bin":"96.000000"},"28"],[{"bin":"97.000000"},"34"],[{"bin":"98.000000"},"23"],[{"bin":"99.000000"},"25"],[{"bin":"100.000000"},"26"],[{"bin":"101.000000"},"24"],[{"bin":"102.000000"},"35"],[{"bin":"103.000000"},"33"],[{"bin":"104.000000"},"26"],[{"bin":"105.000000"},"21"],[{"bin":"106.000000"},"14"],[{"bin":"107.000000"},"19"],[{"bin":"108.000000"},"13"],[{"bin":"109.000000"},"16"],[{"bin":"110.000000"},"11"],[{"bin":"111.000000"},"10"],[{"bin":"112.000000"},"9"],[{"bin":"113.000000"},"10"],[{"bin":"114.000000"},"11"],[{"bin":"115.000000"},"4"],[{"bin":"116.000000"},"11"],[{"bin":"117.000000"},"18"],[{"bin":"118.000000"},"23"],[{"bin":"119.000000"},"13"],[{"bin":"120.000000"},"12"],[{"bin":"121.000000"},"6"],[{"bin":"122.000000"},"11"],[{"bin":"123.000000"},"12"],[{"bin":"124.000000"},"5"],[{"bin":"125.000000"},"5"],[{"bin":"126.000000"},"8"],[{"bin":"127.000000"},"7"],[{"bin":"128.000000"},"6"],[{"bin":"129.000000"},"10"],[{"bin":"130.000000"},"7"],[{"bin":"131.000000"},"11"],[{"bin":"132.000000"},"11"],[{"bin":"133.000000"},"12"],[{"bin":"134.000000"},"10"],[{"bin":"135.000000"},"10"],[{"bin":"136.000000"},"6"],[{"bin":"137.000000"},"12"],[{"bin":"138.000000"},"11"],[{"bin":"139.000000"},"22"],[{"bin":"140.000000"},"16"],[{"bin":"141.000000"},"16"],[{"bin":"142.000000"},"12"],[{"bin":"143.000000"},"19"],[{"bin":"144.000000"},"16"],[{"bin":"145.000000"},"16"],[{"bin":"146.000000"},"11"],[{"bin":"147.000000"},"8"],[{"bin":"148.000000"},"7"],[{"bin":"149.000000"},"9"],[{"bin":"150.000000"},"16"],[{"bin":"151.000000"},"11"],[{"bin":"152.000000"},"1"],[{"bin":"153.000000"},"9"],[{"bin":"154.000000"},"5"],[{"bin":"155.000000"},"5"],[{"bin":"156.000000"},"6"],[{"bin":"157.000000"},"4"],[{"bin":"158.000000"},"9"],[{"bin":"159.000000"},"9"],[{"bin":"160.000000"},"5"],[{"bin":"161.000000"},"9"],[{"bin":"162.000000"},"11"],[{"bin":"163.000000"},"8"],[{"bin":"164.000000"},"12"],[{"bin":"165.000000"},"15"],[{"bin":"166.000000"},"26"],[{"bin":"167.000000"},"9"],[{"bin":"168.000000"},"14"],[{"bin":"169.000000"},"13"],[{"bin":"170.000000"},"15"],[{"bin":"171.000000"},"25"],[{"bin":"172.000000"},"19"],[{"bin":"173.000000"},"19"],[{"bin":"174.000000"},"13"],[{"bin":"175.000000"},"10"],[{"bin":"176.000000"},"17"],[{"bin":"177.000000"},"13"],[{"bin":"178.000000"},"24"],[{"bin":"179.000000"},"21"],[{"bin":"180.000000"},"10"],[{"bin":"181.000000"},"12"],[{"bin":"182.000000"},"11"],[{"bin":"183.000000"},"4"],[{"bin":"184.000000"},"12"],[{"bin":"185.000000"},"5"],[{"bin":"186.000000"},"9"],[{"bin":"187.000000"},"9"],[{"bin":"188.000000"},"9"],[{"bin":"189.000000"},"13"],[{"bin":"190.000000"},"8"],[{"bin":"191.000000"},"6"],[{"bin":"192.000000"},"8"],[{"bin":"193.000000"},"13"],[{"bin":"194.000000"},"9"],[{"bin":"195.000000"},"7"],[{"bin":"196.000000"},"14"],[{"bin":"197.000000"},"11"],[{"bin":"198.000000"},"14"],[{"bin":"199.000000"},"20"],[{"bin":"200.000000"},"17"],[{"bin":"201.000000"},"12"],[{"bin":"202.000000"},"22"],[{"bin":"203.000000"},"19"],[{"bin":"204.000000"},"13"],[{"bin":"205.000000"},"18"],[{"bin":"206.000000"},"14"],[{"bin":"207.000000"},"33"],[{"bin":"208.000000"},"32"],[{"bin":"209.000000"},"22"],[{"bin":"210.000000"},"15"],[{"bin":"211.000000"},"24"],[{"bin":"212.000000"},"19"],[{"bin":"213.000000"},"27"],[{"bin":"214.000000"},"31"],[{"bin":"215.000000"},"30"],[{"bin":"216.000000"},"31"],[{"bin":"217.000000"},"22"],[{"bin":"218.000000"},"33"],[{"bin":"219.000000"},"38"],[{"bin":"220.000000"},"29"],[{"bin":"221.000000"},"16"],[{"bin":"222.000000"},"24"],[{"bin":"223.000000"},"18"],[{"bin":"224.000000"},"25"],[{"bin":"225.000000"},"33"],[{"bin":"226.000000"},"26"],[{"bin":"227.000000"},"31"],[{"bin":"228.000000"},"28"],[{"bin":"229.000000"},"33"],[{"bin":"230.000000"},"27"],[{"bin":"231.000000"},"25"],[{"bin":"232.000000"},"28"],[{"bin":"233.000000"},"31"],[{"bin":"234.000000"},"56"],[{"bin":"235.000000"},"56"],[{"bin":"236.000000"},"66"],[{"bin":"237.000000"},"53"],[{"bin":"238.000000"},"40"],[{"bin":"239.000000"},"39"],[{"bin":"240.000000"},"37"],[{"bin":"241.000000"},"37"],[{"bin":"242.000000"},"16"],[{"bin":"243.000000"},"11"],[{"bin":"244.000000"},"11"],[{"bin":"245.000000"},"5"],[{"bin":"246.000000"},"5"],[{"bin":"247.000000"},"7"],[{"bin":"248.000000"},"5"],[{"bin":"249.000000"},"6"],[{"bin":"250.000000"},"5"],[{"bin":"251.000000"},"3"],[{"bin":"253.000000"},"1"]],"r":[[{"bin":"19.000000"},"1"],[{"bin":"20.000000"},"2"],[{"bin":"26.000000"},"2"],[{"bin":"27.000000"},"1"],[{"bin":"28.000000"},"2"],[{"bin":"30.000000"},"4"],[{"bin":"31.000000"},"4"],[{"bin":"32.000000"},"2"],[{"bin":"33.000000"},"1"],[{"bin":"34.000000"},"2"],[{"bin":"35.000000"},"3"],[{"bin":"36.000000"},"4"],[{"bin":"37.000000"},"5"],[{"bin":"38.000000"},"5"],[{"bin":"39.000000"},"3"],[{"bin":"40.000000"},"3"],[{"bin":"41.000000"},"11"],[{"bin":"42.000000"},"3"],[{"bin":"43.000000"},"8"],[{"bin":"44.000000"},"3"],[{"bin":"45.000000"},"6"],[{"bin":"46.000000"},"11"],[{"bin":"47.000000"},"5"],[{"bin":"48.000000"},"7"],[{"bin":"49.000000"},"8"],[{"bin":"50.000000"},"5"],[{"bin":"51.000000"},"12"],[{"bin":"52.000000"},"8"],[{"bin":"53.000000"},"9"],[{"bin":"54.000000"},"18"],[{"bin":"55.000000"},"21"],[{"bin":"56.000000"},"10"],[{"bin":"57.000000"},"25"],[{"bin":"58.000000"},"21"],[{"bin":"59.000000"},"32"],[{"bin":"60.000000"},"17"],[{"bin":"61.000000"},"29"],[{"bin":"62.000000"},"28"],[{"bin":"63.000000"},"26"],[{"bin":"64.000000"},"23"],[{"bin":"65.000000"},"27"],[{"bin":"66.000000"},"19"],[{"bin":"67.000000"},"13"],[{"bin":"68.000000"},"17"],[{"bin":"69.000000"},"12"],[{"bin":"70.000000"},"6"],[{"bin":"71.000000"},"13"],[{"bin":"72.000000"},"8"],[{"bin":"73.000000"},"6"],[{"bin":"74.000000"},"4"],[{"bin":"75.000000"},"2"],[{"bin":"76.000000"},"7"],[{"bin":"77.000000"},"5"],[{"bin":"78.000000"},"2"],[{"bin":"79.000000"},"7"],[{"bin":"80.000000"},"13"],[{"bin":"81.000000"},"11"],[{"bin":"82.000000"},"4"],[{"bin":"83.000000"},"13"],[{"bin":"84.000000"},"4"],[{"bin":"85.000000"},"9"],[{"bin":"86.000000"},"13"],[{"bin":"87.000000"},"13"],[{"bin":"88.000000"},"11"],[{"bin":"89.000000"},"5"],[{"bin":"90.000000"},"4"],[{"bin":"91.000000"},"10"],[{"bin":"92.000000"},"4"],[{"bin":"93.000000"},"5"],[{"bin":"94.000000"},"3"],[{"bin":"95.000000"},"5"],[{"bin":"96.000000"},"4"],[{"bin":"97.000000"},"9"],[{"bin":"98.000000"},"6"],[{"bin":"99.000000"},"3"],[{"bin":"100.000000"},"8"],[{"bin":"101.000000"},"7"],[{"bin":"102.000000"},"6"],[{"bin":"103.000000"},"8"],[{"bin":"104.000000"},"10"],[{"bin":"105.000000"},"3"],[{"bin":"106.000000"},"8"],[{"bin":"107.000000"},"6"],[{"bin":"108.000000"},"5"],[{"bin":"109.000000"},"7"],[{"bin":"110.000000"},"3"],[{"bin":"111.000000"},"9"],[{"bin":"112.000000"},"3"],[{"bin":"113.000000"},"2"],[{"bin":"114.000000"},"5"],[{"bin":"115.000000"},"3"],[{"bin":"116.000000"},"6"],[{"bin":"117.000000"},"5"],[{"bin":"118.000000"},"6"],[{"bin":"119.000000"},"3"],[{"bin":"120.000000"},"5"],[{"bin":"121.000000"},"4"],[{"bin":"122.000000"},"7"],[{"bin":"123.000000"},"9"],[{"bin":"124.000000"},"3"],[{"bin":"125.000000"},"10"],[{"bin":"126.000000"},"11"],[{"bin":"127.000000"},"1"],[{"bin":"128.000000"},"11"],[{"bin":"129.000000"},"5"],[{"bin":"130.000000"},"7"],[{"bin":"131.000000"},"5"],[{"bin":"132.000000"},"5"],[{"bin":"133.000000"},"7"],[{"bin":"134.000000"},"8"],[{"bin":"135.000000"},"5"],[{"bin":"136.000000"},"7"],[{"bin":"137.000000"},"5"],[{"bin":"138.000000"},"9"],[{"bin":"139.000000"},"9"],[{"bin":"140.000000"},"7"],[{"bin":"141.000000"},"12"],[{"bin":"142.000000"},"9"],[{"bin":"143.000000"},"15"],[{"bin":"144.000000"},"9"],[{"bin":"145.000000"},"12"],[{"bin":"146.000000"},"9"],[{"bin":"147.000000"},"13"],[{"bin":"148.000000"},"8"],[{"bin":"149.000000"},"8"],[{"bin":"150.000000"},"12"],[{"bin":"151.000000"},"10"],[{"bin":"152.000000"},"8"],[{"bin":"153.000000"},"12"],[{"bin":"154.000000"},"13"],[{"bin":"155.000000"},"11"],[{"bin":"156.000000"},"12"],[{"bin":"157.000000"},"8"],[{"bin":"158.000000"},"10"],[{"bin":"159.000000"},"11"],[{"bin":"160.000000"},"14"],[{"bin":"161.000000"},"4"],[{"bin":"162.000000"},"6"],[{"bin":"163.000000"},"8"],[{"bin":"164.000000"},"14"],[{"bin":"165.000000"},"4"],[{"bin":"166.000000"},"7"],[{"bin":"167.000000"},"6"],[{"bin":"168.000000"},"11"],[{"bin":"169.000000"},"6"],[{"bin":"170.000000"},"7"],[{"bin":"171.000000"},"9"],[{"bin":"172.000000"},"6"],[{"bin":"173.000000"},"6"],[{"bin":"174.000000"},"9"],[{"bin":"175.000000"},"6"],[{"bin":"176.000000"},"10"],[{"bin":"177.000000"},"4"],[{"bin":"178.000000"},"9"],[{"bin":"179.000000"},"10"],[{"bin":"180.000000"},"9"],[{"bin":"181.000000"},"8"],[{"bin":"182.000000"},"12"],[{"bin":"183.000000"},"17"],[{"bin":"184.000000"},"20"],[{"bin":"185.000000"},"7"],[{"bin":"186.000000"},"7"],[{"bin":"187.000000"},"17"],[{"bin":"188.000000"},"8"],[{"bin":"189.000000"},"7"],[{"bin":"190.000000"},"10"],[{"bin":"191.000000"},"12"],[{"bin":"192.000000"},"10"],[{"bin":"193.000000"},"11"],[{"bin":"194.000000"},"6"],[{"bin":"195.000000"},"11"],[{"bin":"196.000000"},"9"],[{"bin":"197.000000"},"20"],[{"bin":"198.000000"},"9"],[{"bin":"199.000000"},"13"],[{"bin":"200.000000"},"11"],[{"bin":"201.000000"},"14"],[{"bin":"202.000000"},"12"],[{"bin":"203.000000"},"11"],[{"bin":"204.000000"},"16"],[{"bin":"205.000000"},"9"],[{"bin":"206.000000"},"12"],[{"bin":"207.000000"},"10"],[{"bin":"208.000000"},"11"],[{"bin":"209.000000"},"5"],[{"bin":"210.000000"},"11"],[{"bin":"211.000000"},"19"],[{"bin":"212.000000"},"17"],[{"bin":"213.000000"},"34"],[{"bin":"214.000000"},"38"],[{"bin":"215.000000"},"61"],[{"bin":"216.000000"},"54"],[{"bin":"217.000000"},"62"],[{"bin":"218.000000"},"82"],[{"bin":"219.000000"},"90"],[{"bin":"220.000000"},"89"],[{"bin":"221.000000"},"73"],[{"bin":"222.000000"},"62"],[{"bin":"223.000000"},"46"],[{"bin":"224.000000"},"42"],[{"bin":"225.000000"},"41"],[{"bin":"226.000000"},"22"],[{"bin":"227.000000"},"33"],[{"bin":"228.000000"},"37"],[{"bin":"229.000000"},"18"],[{"bin":"230.000000"},"38"],[{"bin":"231.000000"},"38"],[{"bin":"232.000000"},"37"],[{"bin":"233.000000"},"36"],[{"bin":"234.000000"},"30"],[{"bin":"235.000000"},"33"],[{"bin":"236.000000"},"26"],[{"bin":"237.000000"},"34"],[{"bin":"238.000000"},"45"],[{"bin":"239.000000"},"32"],[{"bin":"240.000000"},"25"],[{"bin":"241.000000"},"53"],[{"bin":"242.000000"},"56"],[{"bin":"243.000000"},"57"],[{"bin":"244.000000"},"73"],[{"bin":"245.000000"},"61"],[{"bin":"246.000000"},"72"],[{"bin":"247.000000"},"66"],[{"bin":"248.000000"},"63"],[{"bin":"249.000000"},"48"],[{"bin":"250.000000"},"40"],[{"bin":"251.000000"},"37"],[{"bin":"252.000000"},"25"],[{"bin":"253.000000"},"24"],[{"bin":"254.000000"},"12"],[{"bin":"255.000000"},"26"]]}}}]}